{"version":"1.0","createdDate":"2024-11-08T21:43:39Z","modelEntity":{"modelURL":"Models\/scrabbleDetectorWithRotation%202%20copy%202.mlmodel","preferredFilename":"","id":"9C5D899D-259E-4151-8BE4-323B17C5EA84","title":"","experimentID":"87B487F3-DBDF-41B6-A85F-D18B1A072BDC","version":"1.0","createdDate":"2024-11-08T21:43:39Z","modifiedDate":"2024-11-08T21:43:39Z"},"activityEntities":["trainingPaused",[{"title":"Training Paused","subtitle":"45 iterations","id":"EDAE966E-8559-4496-A8C1-73A804BAE617","createdDate":"2024-11-08T22:00:13Z","event":"trainingPaused"},{"title":"Training Paused","createdDate":"2024-11-12T22:13:28Z","id":"66B11D9E-36AA-43FF-A0C1-691A40F8A322","event":"trainingPaused","subtitle":"325 iterations"},{"subtitle":"345 iterations","id":"F5CD2109-1B72-48DA-BC7A-6C510A78D5D7","event":"trainingPaused","createdDate":"2024-11-12T22:28:09Z","title":"Training Paused"}],"trainingResumed",[{"title":"Training Resumed","event":"trainingResumed","createdDate":"2024-11-12T21:10:29Z","id":"5376DC97-37BC-4717-A75A-8ECF80560439","subtitle":"1,200 iterations"},{"subtitle":"1,200 iterations","id":"04BAA03E-E0B8-4BAC-A684-DEF35677326E","createdDate":"2024-11-12T22:22:16Z","event":"trainingResumed","title":"Training Resumed"}],"snapshotCreated",[{"subtitle":"Snapshot created at iteration 230","id":"27E2C644-DD1D-4C5C-8E88-0372F77F6084","createdDate":"2024-11-12T21:52:21Z","event":"snapshotCreated","title":"Snapshot Saved"},{"id":"B8148FCF-038F-4B90-AEA6-1110EE9504AD","title":"Snapshot Saved","subtitle":"Snapshot created at iteration 320","event":"snapshotCreated","createdDate":"2024-11-12T22:14:24Z"}],"experimentCreated",[{"subtitle":"scrabbleDetectorWithRotation 2 copy 2","createdDate":"2024-11-08T21:43:39Z","title":"Model Source Created","id":"34D57A52-E49B-4312-9114-46C615C241D7","event":"experimentCreated"}],"trainingStarted",[{"title":"Training Started","subtitle":"1,200 iterations","event":"trainingStarted","id":"B0F47302-23F0-4007-9667-8D8AB6806CD6","createdDate":"2024-11-08T21:45:56Z"}],"validationDataAdded",[{"id":"6C3DA223-2272-476E-9BA3-8F7E3EC7EAD1","title":"Validation Data Added","subtitle":"valid","createdDate":"2024-11-08T21:43:39Z","event":"validationDataAdded"}],"trainingDataAdded",[{"createdDate":"2024-11-08T21:43:39Z","title":"Training Data Added","id":"96C04268-1194-4DFC-AAD9-29E4BF889556","event":"trainingDataAdded","subtitle":"train"}]],"contentDataResult":{"createdDate":"2024-11-01T20:21:59Z"},"id":"0DF2994C-AFB3-4B23-A36B-CB166D1F486E","evaluationContainerEntity":{"modifiedDate":"2024-11-12T22:28:09Z","validationEvaluationEntity":{"dataSourceID":"1518180A-7840-49F1-B4DC-AA181FA96891","createdDate":"2024-11-08T21:43:39Z","dataResult":{"dataURL":"file:\/\/\/Users\/teerthrajparmar\/development\/BoardSolverData\/finalRotatedImages\/valid\/","classesCount":28,"itemsCount":3,"createdDate":"2024-11-08T21:43:39Z","dataSourceID":"1518180A-7840-49F1-B4DC-AA181FA96891","dataAnalysis":{"classifierAnalysis":{},"issues":[{"severity":"debug","description":"28 classes found, including A, E, I"},{"severity":"warning","description":"Less than 50 total images found - add more to improve model validation"},{"description":"Smallest class is \"Q\" with 1 images","severity":"debug"},{"severity":"debug","description":"Largest class is \"A\" with 18 images"}],"objectDetectorAnalysis":{"details":{},"labelStats":{"P":5,"F":1,"D":5,"G":6,"E":17,"L":7,"U":8,"T":8,"I":13,"X":4,"Y":2,"Board":3,"K":2,"R":10,"V":5,"W":3,"H":4,"Q":1,"Blank":4,"J":2,"M":6,"Z":2,"A":18,"O":10,"B":4,"C":2,"N":8,"S":3}},"summary":{"counterExamples":0,"classCount":28,"canUseValidation":1,"sampleCount":3,"suggestedMaxIterations":4000}}},"id":"21e48977-6314-43ac-a310-b92c2b27f4f2","analysedDataType":"datasource"},"trainingEvaluationEntity":{"id":"8505fdc7-be6b-4f6e-9d98-1177d685ef79","analysedDataType":"none","dataResult":{"dataURL":"file:\/\/\/Users\/teerthrajparmar\/development\/BoardSolverData\/finalRotatedImages\/train\/","classesCount":28,"itemsCount":48,"createdDate":"2024-11-08T21:43:39Z","dataSourceID":"49E1FB54-40D0-4E54-8FF6-4B6AF3BC6C75","dataAnalysis":{"issues":[{"description":"28 classes found, including A, I, E","severity":"debug"},{"description":"Less than 50 total images found - add more to improve model validation","severity":"warning"},{"severity":"debug","description":"Smallest class is \"J\" with 36 images"},{"severity":"debug","description":"Largest class is \"A\" with 276 images"}],"summary":{"canUseValidation":1,"classCount":28,"sampleCount":48,"counterExamples":0,"suggestedMaxIterations":17000},"objectDetectorAnalysis":{"labelStats":{"Q":39,"R":174,"N":144,"H":81,"G":60,"D":96,"X":51,"P":84,"V":75,"C":51,"F":42,"Y":42,"B":57,"W":75,"Board":48,"K":42,"U":144,"O":180,"M":96,"S":81,"J":36,"T":129,"L":132,"Blank":45,"I":270,"A":276,"Z":45,"E":264},"details":{}},"classifierAnalysis":{}}},"dataSourceID":"49E1FB54-40D0-4E54-8FF6-4B6AF3BC6C75","createdDate":"2024-11-08T21:43:39Z"},"id":"67450fe7-dffa-4456-a14a-44381e37e378","evaluationEntities":[],"createdDate":"2024-11-12T22:28:09Z","testingEvaluationEntity":{"createdDate":"2024-11-08T21:43:39Z","id":"567ebb84-5f64-4721-9989-fa6989748446","dataSourceID":"F3942739-C296-4D38-8CE9-EEE291DB399A","dataResult":{"dataSourceID":"F3942739-C296-4D38-8CE9-EEE291DB399A","dataURL":"file:\/\/\/Users\/teerthrajparmar\/development\/BoardSolverData\/finalRotatedImages\/test\/","classesCount":27,"dataAnalysis":{"issues":[{"severity":"debug","description":"27 classes found, including A, I, R"},{"severity":"warning","description":"Less than 50 total images found - add more to improve model validation"},{"description":"Smallest class is \"C\" with 1 images","severity":"debug"},{"description":"Largest class is \"A\" with 24 images","severity":"debug"}],"objectDetectorAnalysis":{"labelStats":{"P":6,"F":4,"J":3,"O":12,"L":12,"S":8,"U":12,"G":8,"N":14,"D":8,"I":24,"W":2,"K":2,"R":19,"V":4,"E":18,"Q":4,"T":8,"A":24,"H":8,"Board":5,"B":3,"X":4,"M":7,"Y":4,"Z":4,"C":1},"details":{}},"classifierAnalysis":{},"summary":{"sampleCount":4,"counterExamples":0,"suggestedMaxIterations":5000,"classCount":27,"canUseValidation":1}},"itemsCount":4,"createdDate":"2024-11-08T21:43:39Z"},"analysedDataType":"datasource"},"previewType":"objectDetector"},"title":"scrabbleDetectorWithRotation 2 copy 2","state":"canceled","settingEntity":{"seedType":"default","odGridWidth":25,"transferLearningEmbeddingType":"dynamic","handPoseClassifierAugmentations":[],"odGridHeight":25,"featureNames":[],"harVideoAugmentations":0,"handActionClassifierAugmentations":[],"odAlgorithmType":"darknetYolo","styleTransferAlgorithmType":"image","iterationCount":1200,"algorithmType":"maxEnt","augmentations":[],"taskType":"objectDetector","recommendedIterationCount":17000},"snapshotRole":{"withSnapshots":["DB437EB3-97CA-4C93-BFD9-54C8A1AFD7C2","BD0F593E-9262-426E-85C2-324A870B8D95"]},"validationEntity":{"analysedDataType":"datasource","dataResult":{"dataURL":"file:\/\/\/Users\/teerthrajparmar\/development\/BoardSolverData\/finalRotatedImages\/valid\/","createdDate":"2024-11-08T21:43:39Z","classesCount":28,"itemsCount":3,"dataAnalysis":{"objectDetectorAnalysis":{"details":{},"labelStats":{"N":8,"O":10,"P":5,"Blank":4,"B":4,"Q":1,"X":4,"R":10,"I":13,"K":2,"U":8,"E":17,"V":5,"F":1,"Y":2,"A":18,"C":2,"J":2,"S":3,"H":4,"Board":3,"D":5,"L":7,"Z":2,"M":6,"T":8,"G":6,"W":3}},"summary":{"suggestedMaxIterations":4000,"sampleCount":3,"counterExamples":0,"classCount":28,"canUseValidation":1},"issues":[{"description":"28 classes found, including A, E, I","severity":"debug"},{"description":"Less than 50 total images found - add more to improve model validation","severity":"warning"},{"severity":"debug","description":"Smallest class is \"Q\" with 1 images"},{"description":"Largest class is \"A\" with 18 images","severity":"debug"}],"classifierAnalysis":{}},"dataSourceID":"1518180A-7840-49F1-B4DC-AA181FA96891"},"dataSourceID":"1518180A-7840-49F1-B4DC-AA181FA96891"},"modifiedDate":"2024-11-12T22:28:09Z","evaluationState":"uninitialized","preferredFilename":"scrabbleDetectorWithRotation 2 copy 2","evaluationEntity":{"analysedDataType":"none","id":"2da0b072-2fc3-40c7-83be-84e4fdeb1adb","dataResult":{}},"trainingEntity":{"resumableCheckpointURL":"Checkpoints\/0DF2994C-AFB3-4B23-A36B-CB166D1F486E.scrabbleDetectorWithRotation2copy2.checkpoint","snapshottableCheckpoints":{"340":{"modelURL":"file:\/\/\/Users\/teerthrajparmar\/Library\/Caches\/com.apple.dt.createml\/projects\/EB82AE05-2BC3-4BCF-94A7-5AD7AFF1B32233968d2ea6edb189a466bbfab88d829d1c8088a7\/sessions\/checkpoint.sessions\/0DF2994C-AFB3-4B23-A36B-CB166D1F486E\/training-000000340.checkpoint.model\/checkpointModel.mlmodel","iteration":340,"createdDate":"2024-11-12T22:27:10Z"}},"dataResult":{"dataAnalysis":{"objectDetectorAnalysis":{"labelStats":{"D":96,"N":144,"V":75,"U":144,"I":270,"E":264,"R":174,"S":81,"M":96,"Board":48,"P":84,"F":42,"T":129,"K":42,"O":180,"J":36,"A":276,"B":57,"H":81,"Y":42,"Q":39,"G":60,"L":132,"Z":45,"W":75,"Blank":45,"C":51,"X":51},"details":{}},"summary":{"suggestedMaxIterations":17000,"counterExamples":0,"classCount":28,"canUseValidation":1,"sampleCount":48},"issues":[{"severity":"debug","description":"28 classes found, including A, I, E"},{"severity":"warning","description":"Less than 50 total images found - add more to improve model validation"},{"description":"Smallest class is \"J\" with 36 images","severity":"debug"},{"severity":"debug","description":"Largest class is \"A\" with 276 images"}],"classifierAnalysis":{}},"dataURL":"file:\/\/\/Users\/teerthrajparmar\/development\/BoardSolverData\/finalRotatedImages\/train\/","classesCount":28,"createdDate":"2024-11-08T21:43:39Z","dataSourceID":"49E1FB54-40D0-4E54-8FF6-4B6AF3BC6C75","itemsCount":48},"dataSourceID":"49E1FB54-40D0-4E54-8FF6-4B6AF3BC6C75","startTime":"2024-11-12T22:22:16Z","analysedDataType":"datasource","progress":[{"tableDone":false,"odColumnHeader":{"iterationCount":1,"loss":23.926044464111328,"elapsedTime":28.808366},"isLast":false,"count":1,"percentComplete":0,"currentRowIndex":0,"tableIndex":0},{"currentRowIndex":0,"isLast":false,"count":2,"odColumnHeader":{"loss":23.969558715820312,"iterationCount":2,"elapsedTime":41.578481},"tableDone":false,"tableIndex":0,"percentComplete":0},{"tableIndex":0,"isLast":false,"count":3,"tableDone":false,"percentComplete":0,"odColumnHeader":{"elapsedTime":55.145636,"iterationCount":3,"loss":24.048110961914062},"currentRowIndex":0},{"odColumnHeader":{"loss":24.067293167114258,"iterationCount":4,"elapsedTime":70.251069},"tableDone":false,"percentComplete":0,"count":4,"currentRowIndex":0,"tableIndex":0,"isLast":false},{"odColumnHeader":{"iterationCount":5,"loss":24.17823600769043,"elapsedTime":70.251591},"tableDone":false,"count":5,"isLast":false,"tableIndex":0,"percentComplete":0,"currentRowIndex":0},{"percentComplete":0,"tableDone":false,"currentRowIndex":0,"count":7,"isLast":false,"odColumnHeader":{"elapsedTime":236.933735,"loss":23.811410903930664,"iterationCount":7},"tableIndex":0},{"tableDone":false,"isLast":false,"currentRowIndex":0,"percentComplete":0,"odColumnHeader":{"loss":23.701080322265625,"elapsedTime":250.320293,"iterationCount":8},"count":8,"tableIndex":0},{"count":9,"odColumnHeader":{"elapsedTime":263.307563,"loss":23.55004119873047,"iterationCount":9},"currentRowIndex":0,"percentComplete":0,"tableDone":false,"tableIndex":0,"isLast":false},{"count":10,"currentRowIndex":0,"odColumnHeader":{"iterationCount":10,"elapsedTime":0,"loss":23.45566177368164},"percentComplete":0,"isLast":false,"tableIndex":0,"tableDone":false},{"tableIndex":0,"isLast":false,"currentRowIndex":0,"odColumnHeader":{"elapsedTime":290.180491,"iterationCount":11,"loss":23.262388229370117},"percentComplete":0,"count":11,"tableDone":false},{"tableIndex":0,"tableDone":false,"isLast":false,"percentComplete":0,"odColumnHeader":{"iterationCount":12,"elapsedTime":303.853164,"loss":22.986988067626953},"currentRowIndex":0,"count":12},{"percentComplete":0,"tableIndex":0,"odColumnHeader":{"loss":22.756359100341797,"elapsedTime":317.921487,"iterationCount":13},"isLast":false,"tableDone":false,"count":13,"currentRowIndex":0},{"percentComplete":0,"odColumnHeader":{"elapsedTime":331.870561,"loss":22.604825973510742,"iterationCount":14},"currentRowIndex":0,"isLast":false,"count":14,"tableDone":false,"tableIndex":0},{"currentRowIndex":0,"tableDone":false,"odColumnHeader":{"iterationCount":15,"loss":22.377788543701172,"elapsedTime":331.871411},"percentComplete":0,"count":15,"isLast":false,"tableIndex":0},{"isLast":false,"percentComplete":0,"currentRowIndex":0,"tableDone":false,"tableIndex":0,"count":16,"odColumnHeader":{"elapsedTime":358.286685,"iterationCount":16,"loss":22.12759780883789}},{"tableDone":false,"tableIndex":0,"currentRowIndex":0,"count":17,"odColumnHeader":{"loss":21.806303024291992,"elapsedTime":372.736691,"iterationCount":17},"percentComplete":0,"isLast":false},{"currentRowIndex":0,"count":18,"tableIndex":0,"tableDone":false,"isLast":false,"odColumnHeader":{"loss":21.42014503479004,"elapsedTime":386.513549,"iterationCount":18},"percentComplete":0},{"isLast":false,"percentComplete":0,"count":19,"tableIndex":0,"tableDone":false,"odColumnHeader":{"elapsedTime":400.770321,"loss":21.260530471801758,"iterationCount":19},"currentRowIndex":0},{"tableIndex":0,"tableDone":false,"currentRowIndex":0,"count":20,"percentComplete":0,"odColumnHeader":{"iterationCount":20,"elapsedTime":0,"loss":20.85234260559082},"isLast":false},{"count":21,"currentRowIndex":0,"isLast":false,"percentComplete":0,"tableIndex":0,"tableDone":false,"odColumnHeader":{"iterationCount":21,"loss":20.392417907714844,"elapsedTime":449.513551}},{"count":22,"isLast":false,"tableIndex":0,"currentRowIndex":0,"odColumnHeader":{"iterationCount":22,"elapsedTime":464.177585,"loss":19.955921173095703},"tableDone":false,"percentComplete":0},{"count":23,"percentComplete":0,"tableIndex":0,"tableDone":false,"isLast":false,"odColumnHeader":{"elapsedTime":477.811925,"loss":19.646617889404297,"iterationCount":23},"currentRowIndex":0},{"odColumnHeader":{"loss":19.22757911682129,"iterationCount":24,"elapsedTime":492.810658},"tableIndex":0,"count":24,"percentComplete":0,"tableDone":false,"currentRowIndex":0,"isLast":false},{"isLast":false,"percentComplete":0,"currentRowIndex":0,"tableIndex":0,"odColumnHeader":{"loss":18.855472564697266,"elapsedTime":492.810986,"iterationCount":25},"count":25,"tableDone":false},{"tableDone":false,"isLast":false,"tableIndex":0,"currentRowIndex":0,"count":26,"percentComplete":0,"odColumnHeader":{"loss":18.460607528686523,"elapsedTime":520.012417,"iterationCount":26}},{"percentComplete":0,"isLast":false,"count":27,"tableDone":false,"tableIndex":0,"odColumnHeader":{"iterationCount":27,"loss":18.081663131713867,"elapsedTime":533.58326},"currentRowIndex":0},{"tableIndex":0,"currentRowIndex":0,"count":28,"isLast":false,"odColumnHeader":{"loss":17.682424545288086,"iterationCount":28,"elapsedTime":552.108752},"tableDone":false,"percentComplete":0},{"count":29,"tableIndex":0,"currentRowIndex":0,"isLast":false,"odColumnHeader":{"iterationCount":29,"loss":17.3496150970459,"elapsedTime":582.150133},"tableDone":false,"percentComplete":0},{"count":30,"tableDone":false,"currentRowIndex":0,"percentComplete":0,"odColumnHeader":{"iterationCount":30,"loss":17.045469284057617,"elapsedTime":0},"isLast":false,"tableIndex":0},{"tableIndex":0,"isLast":false,"currentRowIndex":0,"tableDone":false,"percentComplete":0,"odColumnHeader":{"elapsedTime":628.598612,"loss":16.70337677001953,"iterationCount":31},"count":31},{"tableDone":false,"tableIndex":0,"currentRowIndex":0,"odColumnHeader":{"iterationCount":32,"loss":16.44120979309082,"elapsedTime":654.646458},"count":32,"isLast":false,"percentComplete":0},{"odColumnHeader":{"elapsedTime":681.951931,"loss":16.197830200195312,"iterationCount":33},"currentRowIndex":0,"isLast":false,"percentComplete":0,"count":33,"tableIndex":0,"tableDone":false},{"count":34,"isLast":false,"odColumnHeader":{"loss":16.067413330078125,"elapsedTime":700.314148,"iterationCount":34},"tableDone":false,"tableIndex":0,"currentRowIndex":0,"percentComplete":0},{"count":35,"tableIndex":0,"odColumnHeader":{"iterationCount":35,"loss":15.812283515930176,"elapsedTime":700.314693},"tableDone":false,"currentRowIndex":0,"isLast":false,"percentComplete":0},{"tableIndex":0,"isLast":false,"percentComplete":0,"count":36,"currentRowIndex":0,"odColumnHeader":{"loss":15.645343780517578,"iterationCount":36,"elapsedTime":728.0551},"tableDone":false},{"isLast":false,"tableDone":false,"odColumnHeader":{"elapsedTime":741.225126,"loss":15.433616638183594,"iterationCount":37},"count":37,"percentComplete":0,"tableIndex":0,"currentRowIndex":0},{"tableIndex":0,"count":38,"isLast":false,"odColumnHeader":{"elapsedTime":754.379251,"loss":15.221883773803711,"iterationCount":38},"percentComplete":0,"tableDone":false,"currentRowIndex":0},{"currentRowIndex":0,"percentComplete":0,"tableIndex":0,"tableDone":false,"odColumnHeader":{"iterationCount":39,"elapsedTime":770.859404,"loss":14.979430198669434},"isLast":false,"count":39},{"currentRowIndex":0,"isLast":false,"tableIndex":0,"odColumnHeader":{"loss":14.772141456604004,"elapsedTime":0,"iterationCount":40},"count":40,"tableDone":false,"percentComplete":0},{"odColumnHeader":{"elapsedTime":28.807633,"loss":14.621906280517578,"iterationCount":41},"tableIndex":0,"tableDone":false,"isLast":false,"percentComplete":0,"currentRowIndex":0,"count":41},{"count":42,"odColumnHeader":{"iterationCount":42,"elapsedTime":41.251153,"loss":14.485469818115234},"isLast":false,"currentRowIndex":0,"percentComplete":0,"tableDone":false,"tableIndex":0},{"odColumnHeader":{"elapsedTime":53.479004,"iterationCount":43,"loss":14.369747161865234},"currentRowIndex":0,"count":43,"tableDone":false,"tableIndex":0,"percentComplete":0,"isLast":false},{"tableDone":false,"currentRowIndex":0,"count":44,"isLast":false,"percentComplete":0,"tableIndex":0,"odColumnHeader":{"iterationCount":44,"elapsedTime":65.238969,"loss":14.225763320922852}},{"odColumnHeader":{"loss":14.145783424377441,"iterationCount":45,"elapsedTime":65.239363},"tableDone":false,"isLast":false,"count":45,"tableIndex":0,"currentRowIndex":0,"percentComplete":0},{"percentComplete":0,"odColumnHeader":{"iterationCount":47,"loss":13.905040740966797,"elapsedTime":101.412087},"tableDone":false,"count":47,"tableIndex":0,"isLast":false,"currentRowIndex":0},{"isLast":false,"count":48,"tableIndex":0,"tableDone":false,"percentComplete":0,"odColumnHeader":{"iterationCount":48,"elapsedTime":113.042329,"loss":13.773466110229492},"currentRowIndex":0},{"tableDone":false,"count":49,"tableIndex":0,"currentRowIndex":0,"isLast":false,"percentComplete":0,"odColumnHeader":{"iterationCount":49,"loss":13.659717559814453,"elapsedTime":124.849196}},{"percentComplete":0,"tableDone":false,"tableIndex":0,"currentRowIndex":0,"count":50,"isLast":false,"odColumnHeader":{"loss":13.58350944519043,"iterationCount":50,"elapsedTime":0}},{"currentRowIndex":0,"isLast":false,"tableDone":false,"count":51,"odColumnHeader":{"loss":13.505066871643066,"elapsedTime":151.48018,"iterationCount":51},"percentComplete":0,"tableIndex":0},{"count":52,"percentComplete":0,"odColumnHeader":{"elapsedTime":164.140133,"iterationCount":52,"loss":13.380513191223145},"tableIndex":0,"tableDone":false,"currentRowIndex":0,"isLast":false},{"odColumnHeader":{"elapsedTime":176.171381,"iterationCount":53,"loss":13.286458969116211},"currentRowIndex":0,"tableIndex":0,"isLast":false,"tableDone":false,"percentComplete":0,"count":53},{"tableDone":false,"currentRowIndex":0,"odColumnHeader":{"iterationCount":54,"loss":13.235881805419922,"elapsedTime":188.259294},"count":54,"tableIndex":0,"isLast":false,"percentComplete":0},{"odColumnHeader":{"iterationCount":55,"loss":13.17404556274414,"elapsedTime":188.259773},"isLast":false,"count":55,"percentComplete":0,"tableDone":false,"tableIndex":0,"currentRowIndex":0},{"count":56,"odColumnHeader":{"elapsedTime":212.60417,"iterationCount":56,"loss":13.080465316772461},"isLast":false,"percentComplete":0,"currentRowIndex":0,"tableDone":false,"tableIndex":0},{"tableIndex":0,"percentComplete":0,"count":57,"isLast":false,"tableDone":false,"odColumnHeader":{"iterationCount":57,"elapsedTime":224.436456,"loss":12.999029159545898},"currentRowIndex":0},{"percentComplete":0,"count":58,"tableIndex":0,"tableDone":false,"odColumnHeader":{"iterationCount":58,"elapsedTime":237.005666,"loss":12.920236587524414},"isLast":false,"currentRowIndex":0},{"isLast":false,"count":59,"tableDone":false,"percentComplete":0,"odColumnHeader":{"iterationCount":59,"elapsedTime":251.600528,"loss":12.942474365234375},"tableIndex":0,"currentRowIndex":0},{"percentComplete":0,"tableDone":false,"isLast":false,"odColumnHeader":{"elapsedTime":0,"loss":12.863679885864258,"iterationCount":60},"tableIndex":0,"count":60,"currentRowIndex":0},{"currentRowIndex":0,"tableDone":false,"isLast":false,"tableIndex":0,"count":61,"odColumnHeader":{"loss":12.752534866333008,"elapsedTime":278.716393,"iterationCount":61},"percentComplete":0},{"count":62,"tableDone":false,"odColumnHeader":{"elapsedTime":290.747852,"loss":12.680190086364746,"iterationCount":62},"currentRowIndex":0,"tableIndex":0,"isLast":false,"percentComplete":0},{"count":63,"odColumnHeader":{"loss":12.689667701721191,"elapsedTime":302.448364,"iterationCount":63},"currentRowIndex":0,"tableDone":false,"isLast":false,"percentComplete":0,"tableIndex":0},{"tableDone":false,"isLast":false,"odColumnHeader":{"iterationCount":64,"loss":12.601024627685547,"elapsedTime":317.646571},"percentComplete":0,"currentRowIndex":0,"tableIndex":0,"count":64},{"currentRowIndex":0,"odColumnHeader":{"loss":12.537583351135254,"elapsedTime":317.646889,"iterationCount":65},"tableDone":false,"isLast":false,"tableIndex":0,"count":65,"percentComplete":0},{"tableDone":false,"tableIndex":0,"percentComplete":0,"isLast":false,"count":66,"currentRowIndex":0,"odColumnHeader":{"iterationCount":66,"loss":12.469220161437988,"elapsedTime":347.591542}},{"currentRowIndex":0,"count":67,"odColumnHeader":{"elapsedTime":361.362501,"loss":12.406542778015137,"iterationCount":67},"isLast":false,"percentComplete":0,"tableIndex":0,"tableDone":false},{"isLast":false,"odColumnHeader":{"iterationCount":68,"elapsedTime":373.700094,"loss":12.305164337158203},"tableDone":false,"currentRowIndex":0,"count":68,"tableIndex":0,"percentComplete":0},{"tableIndex":0,"odColumnHeader":{"iterationCount":69,"loss":12.226019859313965,"elapsedTime":386.532899},"isLast":false,"percentComplete":0,"tableDone":false,"count":69,"currentRowIndex":0},{"count":70,"percentComplete":0,"currentRowIndex":0,"tableDone":false,"odColumnHeader":{"iterationCount":70,"loss":12.174627304077148,"elapsedTime":0},"isLast":false,"tableIndex":0},{"isLast":false,"tableIndex":0,"currentRowIndex":0,"count":71,"percentComplete":0,"tableDone":false,"odColumnHeader":{"elapsedTime":413.370884,"iterationCount":71,"loss":12.078877449035645}},{"count":72,"tableDone":false,"currentRowIndex":0,"tableIndex":0,"isLast":false,"odColumnHeader":{"loss":12.05707836151123,"elapsedTime":425.529703,"iterationCount":72},"percentComplete":0},{"odColumnHeader":{"elapsedTime":438.360117,"iterationCount":73,"loss":12.040996551513672},"count":73,"tableIndex":0,"isLast":false,"percentComplete":0,"currentRowIndex":0,"tableDone":false},{"isLast":false,"currentRowIndex":0,"odColumnHeader":{"loss":12.074589729309082,"iterationCount":74,"elapsedTime":450.319284},"percentComplete":0,"count":74,"tableDone":false,"tableIndex":0},{"tableIndex":0,"count":75,"isLast":false,"tableDone":false,"currentRowIndex":0,"percentComplete":0,"odColumnHeader":{"iterationCount":75,"elapsedTime":450.319692,"loss":12.000445365905762}},{"tableDone":false,"count":76,"isLast":false,"odColumnHeader":{"iterationCount":76,"loss":11.970138549804688,"elapsedTime":475.596868},"currentRowIndex":0,"percentComplete":0,"tableIndex":0},{"tableIndex":0,"count":77,"odColumnHeader":{"iterationCount":77,"loss":11.928529739379883,"elapsedTime":488.961831},"currentRowIndex":0,"percentComplete":0,"isLast":false,"tableDone":false},{"percentComplete":0,"tableDone":false,"tableIndex":0,"isLast":false,"currentRowIndex":0,"odColumnHeader":{"iterationCount":78,"elapsedTime":506.086586,"loss":11.86755657196045},"count":78},{"tableIndex":0,"odColumnHeader":{"elapsedTime":518.435827,"loss":11.784332275390625,"iterationCount":79},"currentRowIndex":0,"percentComplete":0,"tableDone":false,"count":79,"isLast":false},{"count":80,"isLast":false,"tableDone":false,"currentRowIndex":0,"percentComplete":0,"tableIndex":0,"odColumnHeader":{"iterationCount":80,"loss":11.715408325195312,"elapsedTime":0}},{"tableIndex":0,"count":81,"isLast":false,"tableDone":false,"percentComplete":0,"currentRowIndex":0,"odColumnHeader":{"loss":11.705254554748535,"elapsedTime":551.082063,"iterationCount":81}},{"isLast":false,"count":82,"tableIndex":0,"currentRowIndex":0,"tableDone":false,"odColumnHeader":{"elapsedTime":566.039467,"loss":11.717166900634766,"iterationCount":82},"percentComplete":0},{"tableIndex":0,"isLast":false,"percentComplete":0,"currentRowIndex":0,"odColumnHeader":{"iterationCount":83,"elapsedTime":578.476847,"loss":11.6383695602417},"count":83,"tableDone":false},{"odColumnHeader":{"elapsedTime":590.390526,"loss":11.559035301208496,"iterationCount":84},"currentRowIndex":0,"percentComplete":0,"tableDone":false,"isLast":false,"count":84,"tableIndex":0},{"percentComplete":0,"tableDone":false,"currentRowIndex":0,"isLast":false,"odColumnHeader":{"loss":11.504471778869629,"iterationCount":85,"elapsedTime":590.39454},"tableIndex":0,"count":85},{"tableDone":false,"isLast":false,"tableIndex":0,"percentComplete":0,"odColumnHeader":{"elapsedTime":615.056113,"loss":11.425277709960938,"iterationCount":86},"count":86,"currentRowIndex":0},{"percentComplete":0,"isLast":false,"count":87,"tableIndex":0,"currentRowIndex":0,"tableDone":false,"odColumnHeader":{"loss":11.338911056518555,"elapsedTime":627.279934,"iterationCount":87}},{"percentComplete":0,"count":88,"isLast":false,"odColumnHeader":{"loss":11.273245811462402,"elapsedTime":640.195801,"iterationCount":88},"tableIndex":0,"currentRowIndex":0,"tableDone":false},{"count":89,"tableIndex":0,"tableDone":false,"odColumnHeader":{"loss":11.236898422241211,"iterationCount":89,"elapsedTime":652.077577},"percentComplete":0,"isLast":false,"currentRowIndex":0},{"tableIndex":0,"tableDone":false,"percentComplete":0,"currentRowIndex":0,"isLast":false,"odColumnHeader":{"elapsedTime":0,"iterationCount":90,"loss":11.182943344116211},"count":90},{"odColumnHeader":{"iterationCount":91,"loss":11.214823722839355,"elapsedTime":681.657533},"tableIndex":0,"isLast":false,"count":91,"currentRowIndex":0,"percentComplete":0,"tableDone":false},{"count":92,"tableDone":false,"currentRowIndex":0,"tableIndex":0,"isLast":false,"odColumnHeader":{"elapsedTime":695.350739,"iterationCount":92,"loss":11.18174934387207},"percentComplete":0},{"isLast":false,"count":93,"currentRowIndex":0,"tableIndex":0,"tableDone":false,"odColumnHeader":{"loss":11.121907234191895,"iterationCount":93,"elapsedTime":709.344624},"percentComplete":0},{"tableDone":false,"percentComplete":0,"tableIndex":0,"currentRowIndex":0,"odColumnHeader":{"iterationCount":94,"elapsedTime":722.056078,"loss":11.023970603942871},"count":94,"isLast":false},{"tableIndex":0,"odColumnHeader":{"loss":10.967175483703613,"iterationCount":95,"elapsedTime":722.056362},"tableDone":false,"isLast":false,"count":95,"currentRowIndex":0,"percentComplete":0},{"isLast":false,"tableDone":false,"odColumnHeader":{"loss":10.966866493225098,"elapsedTime":746.10084,"iterationCount":96},"currentRowIndex":0,"tableIndex":0,"count":96,"percentComplete":0},{"count":97,"odColumnHeader":{"iterationCount":97,"loss":10.926106452941895,"elapsedTime":757.915967},"isLast":false,"percentComplete":0,"tableIndex":0,"currentRowIndex":0,"tableDone":false},{"count":98,"tableIndex":0,"tableDone":false,"odColumnHeader":{"iterationCount":98,"loss":10.90561580657959,"elapsedTime":769.897408},"percentComplete":0,"isLast":false,"currentRowIndex":0},{"tableDone":false,"tableIndex":0,"isLast":false,"percentComplete":0,"currentRowIndex":0,"count":99,"odColumnHeader":{"loss":10.906678199768066,"elapsedTime":782.003066,"iterationCount":99}},{"tableDone":false,"isLast":false,"odColumnHeader":{"elapsedTime":0,"iterationCount":100,"loss":10.835480690002441},"count":100,"tableIndex":0,"percentComplete":0,"currentRowIndex":0},{"isLast":false,"currentRowIndex":0,"tableDone":false,"odColumnHeader":{"iterationCount":101,"loss":10.795918464660645,"elapsedTime":811.861663},"tableIndex":0,"percentComplete":0,"count":101},{"tableIndex":0,"currentRowIndex":0,"isLast":false,"percentComplete":0,"odColumnHeader":{"elapsedTime":823.678259,"iterationCount":102,"loss":10.795833587646484},"count":102,"tableDone":false},{"percentComplete":0,"tableIndex":0,"count":103,"isLast":false,"odColumnHeader":{"loss":10.751797676086426,"iterationCount":103,"elapsedTime":835.742933},"tableDone":false,"currentRowIndex":0},{"currentRowIndex":0,"percentComplete":0,"odColumnHeader":{"loss":10.72408676147461,"elapsedTime":847.701794,"iterationCount":104},"count":104,"tableIndex":0,"tableDone":false,"isLast":false},{"tableDone":false,"percentComplete":0,"isLast":false,"tableIndex":0,"odColumnHeader":{"iterationCount":105,"loss":10.718522071838379,"elapsedTime":847.702367},"count":105,"currentRowIndex":0},{"count":106,"tableIndex":0,"currentRowIndex":0,"percentComplete":0,"tableDone":false,"isLast":false,"odColumnHeader":{"iterationCount":106,"loss":10.627762794494629,"elapsedTime":871.941634}},{"isLast":false,"odColumnHeader":{"iterationCount":107,"elapsedTime":883.761749,"loss":10.621816635131836},"count":107,"tableDone":false,"tableIndex":0,"percentComplete":0,"currentRowIndex":0},{"count":108,"percentComplete":0,"tableIndex":0,"odColumnHeader":{"elapsedTime":896.070934,"loss":10.577180862426758,"iterationCount":108},"currentRowIndex":0,"tableDone":false,"isLast":false},{"odColumnHeader":{"elapsedTime":907.865999,"iterationCount":109,"loss":10.590911865234375},"percentComplete":0,"currentRowIndex":0,"count":109,"isLast":false,"tableDone":false,"tableIndex":0},{"count":110,"percentComplete":0,"odColumnHeader":{"iterationCount":110,"loss":10.535685539245605,"elapsedTime":0},"isLast":false,"tableIndex":0,"currentRowIndex":0,"tableDone":false},{"odColumnHeader":{"loss":10.443245887756348,"elapsedTime":934.648875,"iterationCount":111},"tableDone":false,"isLast":false,"currentRowIndex":0,"percentComplete":0,"tableIndex":0,"count":111},{"currentRowIndex":0,"percentComplete":0,"odColumnHeader":{"loss":10.417093276977539,"elapsedTime":946.465823,"iterationCount":112},"tableDone":false,"tableIndex":0,"isLast":false,"count":112},{"tableIndex":0,"percentComplete":0,"tableDone":false,"count":113,"currentRowIndex":0,"odColumnHeader":{"iterationCount":113,"loss":10.34646987915039,"elapsedTime":958.589619},"isLast":false},{"tableDone":false,"tableIndex":0,"count":114,"currentRowIndex":0,"percentComplete":0,"isLast":false,"odColumnHeader":{"elapsedTime":971.35732,"iterationCount":114,"loss":10.293309211730957}},{"odColumnHeader":{"iterationCount":115,"elapsedTime":971.357776,"loss":10.289109230041504},"tableDone":false,"count":115,"percentComplete":0,"tableIndex":0,"isLast":false,"currentRowIndex":0},{"currentRowIndex":0,"percentComplete":0,"tableIndex":0,"isLast":false,"count":116,"tableDone":false,"odColumnHeader":{"iterationCount":116,"loss":10.249871253967285,"elapsedTime":996.916215}},{"tableDone":false,"tableIndex":0,"isLast":false,"count":117,"currentRowIndex":0,"odColumnHeader":{"loss":10.197558403015137,"elapsedTime":1009.06487,"iterationCount":117},"percentComplete":0},{"count":118,"currentRowIndex":0,"isLast":false,"percentComplete":0,"tableDone":false,"tableIndex":0,"odColumnHeader":{"iterationCount":118,"elapsedTime":1022.907177,"loss":10.183309555053711}},{"odColumnHeader":{"iterationCount":119,"elapsedTime":1036.265866,"loss":10.139267921447754},"tableIndex":0,"percentComplete":0,"tableDone":false,"currentRowIndex":0,"isLast":false,"count":119},{"tableDone":false,"isLast":false,"odColumnHeader":{"elapsedTime":0,"iterationCount":120,"loss":10.075236320495605},"tableIndex":0,"percentComplete":0,"currentRowIndex":0,"count":120},{"tableIndex":0,"count":121,"odColumnHeader":{"elapsedTime":1063.261891,"loss":9.988929748535156,"iterationCount":121},"isLast":false,"percentComplete":0,"tableDone":false,"currentRowIndex":0},{"tableDone":false,"odColumnHeader":{"loss":10.038650512695312,"elapsedTime":1075.493189,"iterationCount":122},"isLast":false,"tableIndex":0,"percentComplete":0,"currentRowIndex":0,"count":122},{"tableIndex":0,"odColumnHeader":{"iterationCount":123,"loss":9.999191284179688,"elapsedTime":1087.509363},"currentRowIndex":0,"percentComplete":0,"count":123,"isLast":false,"tableDone":false},{"tableIndex":0,"isLast":false,"count":124,"percentComplete":0,"currentRowIndex":0,"tableDone":false,"odColumnHeader":{"elapsedTime":1099.578044,"iterationCount":124,"loss":10.006941795349121}},{"tableDone":false,"percentComplete":0,"tableIndex":0,"isLast":false,"odColumnHeader":{"iterationCount":125,"elapsedTime":1099.57834,"loss":9.958906173706055},"currentRowIndex":0,"count":125},{"percentComplete":0,"odColumnHeader":{"elapsedTime":1123.609569,"loss":9.926129341125488,"iterationCount":126},"tableIndex":0,"tableDone":false,"isLast":false,"count":126,"currentRowIndex":0},{"tableDone":false,"currentRowIndex":0,"isLast":false,"percentComplete":0,"odColumnHeader":{"loss":9.973496437072754,"iterationCount":127,"elapsedTime":1135.138133},"tableIndex":0,"count":127},{"isLast":false,"currentRowIndex":0,"odColumnHeader":{"iterationCount":128,"elapsedTime":1147.047933,"loss":9.954633712768555},"tableDone":false,"tableIndex":0,"count":128,"percentComplete":0},{"count":129,"percentComplete":0,"tableIndex":0,"odColumnHeader":{"iterationCount":129,"loss":9.876882553100586,"elapsedTime":1159.139801},"currentRowIndex":0,"tableDone":false,"isLast":false},{"isLast":false,"tableDone":false,"tableIndex":0,"odColumnHeader":{"iterationCount":130,"loss":9.811863899230957,"elapsedTime":0},"currentRowIndex":0,"percentComplete":0,"count":130},{"tableIndex":0,"percentComplete":0,"count":131,"tableDone":false,"isLast":false,"odColumnHeader":{"elapsedTime":1184.309174,"iterationCount":131,"loss":9.743693351745605},"currentRowIndex":0},{"odColumnHeader":{"elapsedTime":1196.548487,"iterationCount":132,"loss":9.71955394744873},"isLast":false,"currentRowIndex":0,"percentComplete":0,"tableIndex":0,"count":132,"tableDone":false},{"currentRowIndex":0,"odColumnHeader":{"elapsedTime":1208.344682,"loss":9.718146324157715,"iterationCount":133},"count":133,"tableDone":false,"isLast":false,"percentComplete":0,"tableIndex":0},{"tableDone":false,"tableIndex":0,"count":134,"odColumnHeader":{"iterationCount":134,"elapsedTime":1220.30083,"loss":9.595166206359863},"isLast":false,"percentComplete":0,"currentRowIndex":0},{"tableDone":false,"tableIndex":0,"currentRowIndex":0,"count":135,"odColumnHeader":{"iterationCount":135,"elapsedTime":1220.301159,"loss":9.58651351928711},"isLast":false,"percentComplete":0},{"isLast":false,"tableIndex":0,"odColumnHeader":{"loss":9.540512084960938,"elapsedTime":1250.83313,"iterationCount":136},"percentComplete":0,"count":136,"tableDone":false,"currentRowIndex":0},{"tableDone":false,"currentRowIndex":0,"odColumnHeader":{"elapsedTime":1266.07589,"iterationCount":137,"loss":9.53900146484375},"isLast":false,"tableIndex":0,"percentComplete":0,"count":137},{"odColumnHeader":{"elapsedTime":1283.92414,"iterationCount":138,"loss":9.516130447387695},"count":138,"percentComplete":0,"tableDone":false,"tableIndex":0,"isLast":false,"currentRowIndex":0},{"currentRowIndex":0,"odColumnHeader":{"iterationCount":139,"loss":9.504300117492676,"elapsedTime":1298.295658},"tableDone":false,"tableIndex":0,"percentComplete":0,"count":139,"isLast":false},{"tableDone":false,"count":140,"currentRowIndex":0,"odColumnHeader":{"iterationCount":140,"loss":9.420677185058594,"elapsedTime":0},"percentComplete":0,"tableIndex":0,"isLast":false},{"isLast":false,"percentComplete":0,"tableIndex":0,"count":141,"odColumnHeader":{"loss":9.378228187561035,"elapsedTime":1330.403193,"iterationCount":141},"tableDone":false,"currentRowIndex":0},{"odColumnHeader":{"loss":9.37623405456543,"elapsedTime":1343.19308,"iterationCount":142},"tableDone":false,"count":142,"percentComplete":0,"tableIndex":0,"isLast":false,"currentRowIndex":0},{"currentRowIndex":0,"isLast":false,"odColumnHeader":{"iterationCount":143,"loss":9.287396430969238,"elapsedTime":1355.309421},"percentComplete":0,"tableIndex":0,"count":143,"tableDone":false},{"tableIndex":0,"count":144,"isLast":false,"odColumnHeader":{"elapsedTime":1367.25551,"iterationCount":144,"loss":9.23509693145752},"percentComplete":0,"currentRowIndex":0,"tableDone":false},{"currentRowIndex":0,"tableIndex":0,"isLast":false,"tableDone":false,"count":145,"percentComplete":0,"odColumnHeader":{"loss":9.249680519104004,"iterationCount":145,"elapsedTime":1367.255871}},{"isLast":false,"count":146,"percentComplete":0,"tableDone":false,"odColumnHeader":{"iterationCount":146,"loss":9.211286544799805,"elapsedTime":1393.733014},"currentRowIndex":0,"tableIndex":0},{"tableIndex":0,"isLast":false,"percentComplete":0,"count":147,"odColumnHeader":{"loss":9.213671684265137,"elapsedTime":1406.21638,"iterationCount":147},"tableDone":false,"currentRowIndex":0},{"currentRowIndex":0,"isLast":false,"tableIndex":0,"tableDone":false,"count":148,"percentComplete":0,"odColumnHeader":{"elapsedTime":1419.039905,"iterationCount":148,"loss":9.198221206665039}},{"isLast":false,"percentComplete":0,"tableIndex":0,"tableDone":false,"count":149,"currentRowIndex":0,"odColumnHeader":{"iterationCount":149,"loss":9.119224548339844,"elapsedTime":1432.955019}},{"odColumnHeader":{"iterationCount":150,"elapsedTime":0,"loss":9.05312442779541},"currentRowIndex":0,"tableIndex":0,"percentComplete":0,"isLast":false,"count":150,"tableDone":false},{"isLast":false,"tableIndex":0,"currentRowIndex":0,"percentComplete":0,"tableDone":false,"count":151,"odColumnHeader":{"elapsedTime":1462.412142,"iterationCount":151,"loss":9.037718772888184}},{"percentComplete":0,"count":152,"odColumnHeader":{"iterationCount":152,"loss":9.025090217590332,"elapsedTime":1476.638451},"tableIndex":0,"isLast":false,"currentRowIndex":0,"tableDone":false},{"count":153,"percentComplete":0,"odColumnHeader":{"loss":8.954595565795898,"iterationCount":153,"elapsedTime":1492.621514},"tableDone":false,"tableIndex":0,"currentRowIndex":0,"isLast":false},{"percentComplete":0,"currentRowIndex":0,"isLast":false,"tableIndex":0,"tableDone":false,"count":154,"odColumnHeader":{"loss":8.873434066772461,"elapsedTime":1506.530661,"iterationCount":154}},{"isLast":false,"currentRowIndex":0,"tableIndex":0,"count":155,"tableDone":false,"odColumnHeader":{"loss":8.820694923400879,"elapsedTime":1506.531076,"iterationCount":155},"percentComplete":0},{"tableDone":false,"isLast":false,"currentRowIndex":0,"percentComplete":0,"tableIndex":0,"count":156,"odColumnHeader":{"loss":8.832640647888184,"iterationCount":156,"elapsedTime":1535.786611}},{"isLast":false,"count":157,"tableIndex":0,"tableDone":false,"percentComplete":0,"currentRowIndex":0,"odColumnHeader":{"loss":8.818061828613281,"iterationCount":157,"elapsedTime":1548.042256}},{"tableIndex":0,"odColumnHeader":{"loss":8.782147407531738,"elapsedTime":1559.891727,"iterationCount":158},"percentComplete":0,"count":158,"isLast":false,"tableDone":false,"currentRowIndex":0},{"count":159,"tableDone":false,"tableIndex":0,"currentRowIndex":0,"percentComplete":0,"odColumnHeader":{"loss":8.7434720993042,"elapsedTime":1571.557383,"iterationCount":159},"isLast":false},{"count":160,"odColumnHeader":{"iterationCount":160,"loss":8.762304306030273,"elapsedTime":0},"tableDone":false,"percentComplete":0,"isLast":false,"tableIndex":0,"currentRowIndex":0},{"count":161,"percentComplete":0,"tableIndex":0,"isLast":false,"odColumnHeader":{"elapsedTime":1597.676162,"loss":8.720049858093262,"iterationCount":161},"tableDone":false,"currentRowIndex":0},{"currentRowIndex":0,"odColumnHeader":{"iterationCount":162,"loss":8.696919441223145,"elapsedTime":1609.709406},"percentComplete":0,"tableDone":false,"tableIndex":0,"count":162,"isLast":false},{"odColumnHeader":{"loss":8.743032455444336,"iterationCount":163,"elapsedTime":1621.781463},"count":163,"currentRowIndex":0,"percentComplete":0,"tableIndex":0,"isLast":false,"tableDone":false},{"tableIndex":0,"isLast":false,"count":164,"currentRowIndex":0,"percentComplete":0,"odColumnHeader":{"loss":8.662558555603027,"iterationCount":164,"elapsedTime":1633.673112},"tableDone":false},{"tableIndex":0,"isLast":false,"odColumnHeader":{"elapsedTime":1633.673886,"iterationCount":165,"loss":8.622726440429688},"tableDone":false,"currentRowIndex":0,"percentComplete":0,"count":165},{"currentRowIndex":0,"percentComplete":0,"tableDone":false,"tableIndex":0,"odColumnHeader":{"loss":8.614635467529297,"iterationCount":166,"elapsedTime":1658.567158},"count":166,"isLast":false},{"tableDone":false,"odColumnHeader":{"iterationCount":167,"loss":8.62613582611084,"elapsedTime":1670.492185},"isLast":false,"count":167,"tableIndex":0,"currentRowIndex":0,"percentComplete":0},{"tableIndex":0,"tableDone":false,"percentComplete":0,"isLast":false,"odColumnHeader":{"elapsedTime":1682.614326,"loss":8.553108215332031,"iterationCount":168},"count":168,"currentRowIndex":0},{"percentComplete":0,"isLast":false,"currentRowIndex":0,"count":169,"odColumnHeader":{"elapsedTime":1695.271161,"iterationCount":169,"loss":8.511456489562988},"tableIndex":0,"tableDone":false},{"count":170,"tableIndex":0,"tableDone":false,"isLast":false,"percentComplete":0,"currentRowIndex":0,"odColumnHeader":{"iterationCount":170,"loss":8.487889289855957,"elapsedTime":0}},{"currentRowIndex":0,"tableDone":false,"count":171,"odColumnHeader":{"iterationCount":171,"loss":8.446435928344727,"elapsedTime":1720.718095},"percentComplete":0,"tableIndex":0,"isLast":false},{"isLast":false,"odColumnHeader":{"iterationCount":172,"elapsedTime":1732.485239,"loss":8.426957130432129},"tableDone":false,"count":172,"tableIndex":0,"currentRowIndex":0,"percentComplete":0},{"isLast":false,"percentComplete":0,"count":173,"tableDone":false,"tableIndex":0,"currentRowIndex":0,"odColumnHeader":{"iterationCount":173,"loss":8.397601127624512,"elapsedTime":1744.403834}},{"percentComplete":0,"isLast":false,"tableDone":false,"tableIndex":0,"odColumnHeader":{"iterationCount":174,"loss":8.349435806274414,"elapsedTime":1756.736495},"currentRowIndex":0,"count":174},{"isLast":false,"currentRowIndex":0,"percentComplete":0,"odColumnHeader":{"loss":8.298933029174805,"elapsedTime":1756.73705,"iterationCount":175},"tableDone":false,"count":175,"tableIndex":0},{"tableDone":false,"isLast":false,"odColumnHeader":{"loss":8.232330322265625,"elapsedTime":1780.477131,"iterationCount":176},"count":176,"tableIndex":0,"currentRowIndex":0,"percentComplete":0},{"count":177,"odColumnHeader":{"loss":8.203483581542969,"iterationCount":177,"elapsedTime":1792.176365},"tableIndex":0,"currentRowIndex":0,"percentComplete":0,"tableDone":false,"isLast":false},{"count":178,"odColumnHeader":{"loss":8.259922981262207,"elapsedTime":1803.984799,"iterationCount":178},"percentComplete":0,"tableDone":false,"tableIndex":0,"currentRowIndex":0,"isLast":false},{"tableIndex":0,"isLast":false,"odColumnHeader":{"iterationCount":179,"loss":8.191417694091797,"elapsedTime":1816.338154},"tableDone":false,"percentComplete":0,"currentRowIndex":0,"count":179},{"percentComplete":0,"tableDone":false,"currentRowIndex":0,"count":180,"tableIndex":0,"odColumnHeader":{"loss":8.20540714263916,"elapsedTime":0,"iterationCount":180},"isLast":false},{"count":181,"currentRowIndex":0,"odColumnHeader":{"loss":8.195175170898438,"elapsedTime":1841.211258,"iterationCount":181},"tableIndex":0,"percentComplete":0,"tableDone":false,"isLast":false},{"isLast":false,"currentRowIndex":0,"tableIndex":0,"odColumnHeader":{"elapsedTime":1853.042883,"iterationCount":182,"loss":8.159073829650879},"tableDone":false,"percentComplete":0,"count":182},{"tableIndex":0,"odColumnHeader":{"iterationCount":183,"loss":8.161757469177246,"elapsedTime":1865.078729},"percentComplete":0,"currentRowIndex":0,"tableDone":false,"isLast":false,"count":183},{"tableDone":false,"count":184,"percentComplete":0,"isLast":false,"tableIndex":0,"currentRowIndex":0,"odColumnHeader":{"elapsedTime":1879.247227,"iterationCount":184,"loss":8.125042915344238}},{"tableIndex":0,"percentComplete":0,"count":185,"tableDone":false,"currentRowIndex":0,"isLast":false,"odColumnHeader":{"loss":8.104205131530762,"elapsedTime":1879.247956,"iterationCount":185}},{"percentComplete":0,"currentRowIndex":0,"odColumnHeader":{"elapsedTime":1906.499806,"loss":8.061643600463867,"iterationCount":186},"count":186,"tableDone":false,"tableIndex":0,"isLast":false},{"tableDone":false,"tableIndex":0,"percentComplete":0,"odColumnHeader":{"iterationCount":187,"elapsedTime":1918.524359,"loss":8.083436012268066},"isLast":false,"currentRowIndex":0,"count":187},{"count":188,"odColumnHeader":{"loss":8.056770324707031,"elapsedTime":1930.7375,"iterationCount":188},"tableDone":false,"tableIndex":0,"percentComplete":0,"currentRowIndex":0,"isLast":false},{"count":189,"odColumnHeader":{"elapsedTime":1942.790386,"iterationCount":189,"loss":8.046143531799316},"currentRowIndex":0,"isLast":false,"tableIndex":0,"percentComplete":0,"tableDone":false},{"currentRowIndex":0,"count":190,"tableDone":false,"percentComplete":0,"isLast":false,"odColumnHeader":{"loss":8.043646812438965,"elapsedTime":0,"iterationCount":190},"tableIndex":0},{"isLast":false,"count":191,"percentComplete":0,"odColumnHeader":{"loss":8.069707870483398,"elapsedTime":1970.564355,"iterationCount":191},"tableIndex":0,"tableDone":false,"currentRowIndex":0},{"tableDone":false,"tableIndex":0,"count":192,"odColumnHeader":{"iterationCount":192,"loss":8.038751602172852,"elapsedTime":1984.05053},"percentComplete":0,"currentRowIndex":0,"isLast":false},{"tableDone":false,"isLast":false,"currentRowIndex":0,"tableIndex":0,"count":193,"percentComplete":0,"odColumnHeader":{"loss":8.040739059448242,"elapsedTime":1997.815985,"iterationCount":193}},{"percentComplete":0,"currentRowIndex":0,"count":194,"isLast":false,"tableIndex":0,"odColumnHeader":{"loss":8.033553123474121,"elapsedTime":2010.372379,"iterationCount":194},"tableDone":false},{"tableIndex":0,"odColumnHeader":{"loss":7.977290630340576,"elapsedTime":2010.372635,"iterationCount":195},"tableDone":false,"currentRowIndex":0,"count":195,"percentComplete":0,"isLast":false},{"isLast":false,"count":196,"odColumnHeader":{"loss":7.9418792724609375,"iterationCount":196,"elapsedTime":2034.109097},"percentComplete":0,"currentRowIndex":0,"tableDone":false,"tableIndex":0},{"currentRowIndex":0,"isLast":false,"odColumnHeader":{"iterationCount":197,"elapsedTime":2046.184853,"loss":7.8859734535217285},"percentComplete":0,"count":197,"tableDone":false,"tableIndex":0},{"tableDone":false,"isLast":false,"tableIndex":0,"count":198,"percentComplete":0,"odColumnHeader":{"loss":7.8646697998046875,"elapsedTime":2061.005021,"iterationCount":198},"currentRowIndex":0},{"percentComplete":0,"count":199,"tableIndex":0,"tableDone":false,"currentRowIndex":0,"odColumnHeader":{"iterationCount":199,"loss":7.902056694030762,"elapsedTime":2075.31602},"isLast":false},{"odColumnHeader":{"elapsedTime":0,"loss":7.862246513366699,"iterationCount":200},"tableIndex":0,"tableDone":false,"currentRowIndex":0,"count":200,"percentComplete":0,"isLast":false},{"count":201,"currentRowIndex":0,"tableIndex":0,"tableDone":false,"percentComplete":0,"isLast":false,"odColumnHeader":{"loss":7.833475589752197,"elapsedTime":2105.849225,"iterationCount":201}},{"tableIndex":0,"count":202,"odColumnHeader":{"iterationCount":202,"loss":7.828173637390137,"elapsedTime":2118.233416},"currentRowIndex":0,"isLast":false,"tableDone":false,"percentComplete":0},{"percentComplete":0,"tableIndex":0,"isLast":false,"count":203,"currentRowIndex":0,"odColumnHeader":{"elapsedTime":2130.338488,"iterationCount":203,"loss":7.772759437561035},"tableDone":false},{"tableDone":false,"currentRowIndex":0,"odColumnHeader":{"elapsedTime":2141.800209,"iterationCount":204,"loss":7.807816505432129},"tableIndex":0,"isLast":false,"count":204,"percentComplete":0},{"isLast":false,"tableDone":false,"odColumnHeader":{"iterationCount":205,"loss":7.824301242828369,"elapsedTime":2141.800463},"tableIndex":0,"count":205,"percentComplete":0,"currentRowIndex":0},{"percentComplete":0,"count":206,"odColumnHeader":{"iterationCount":206,"elapsedTime":2165.706963,"loss":7.749259948730469},"tableDone":false,"isLast":false,"tableIndex":0,"currentRowIndex":0},{"odColumnHeader":{"iterationCount":207,"elapsedTime":2177.804513,"loss":7.704242706298828},"isLast":false,"tableDone":false,"tableIndex":0,"count":207,"percentComplete":0,"currentRowIndex":0},{"tableIndex":0,"percentComplete":0,"isLast":false,"tableDone":false,"count":208,"odColumnHeader":{"elapsedTime":2190.247326,"iterationCount":208,"loss":7.62664794921875},"currentRowIndex":0},{"tableDone":false,"count":209,"isLast":false,"odColumnHeader":{"loss":7.614022731781006,"elapsedTime":2201.968665,"iterationCount":209},"percentComplete":0,"tableIndex":0,"currentRowIndex":0},{"count":210,"percentComplete":0,"tableDone":false,"tableIndex":0,"odColumnHeader":{"loss":7.583600997924805,"iterationCount":210,"elapsedTime":0},"isLast":false,"currentRowIndex":0},{"percentComplete":0,"count":211,"isLast":false,"currentRowIndex":0,"tableIndex":0,"tableDone":false,"odColumnHeader":{"loss":7.544750690460205,"iterationCount":211,"elapsedTime":2228.030925}},{"currentRowIndex":0,"tableIndex":0,"odColumnHeader":{"iterationCount":212,"loss":7.569740295410156,"elapsedTime":2240.19678},"tableDone":false,"count":212,"percentComplete":0,"isLast":false},{"tableIndex":0,"tableDone":false,"isLast":false,"count":213,"percentComplete":0,"odColumnHeader":{"loss":7.609877109527588,"iterationCount":213,"elapsedTime":2252.191485},"currentRowIndex":0},{"tableIndex":0,"count":214,"percentComplete":0,"odColumnHeader":{"loss":7.61544132232666,"elapsedTime":2264.474339,"iterationCount":214},"isLast":false,"tableDone":false,"currentRowIndex":0},{"isLast":false,"count":215,"percentComplete":0,"tableIndex":0,"currentRowIndex":0,"odColumnHeader":{"loss":7.670574188232422,"elapsedTime":2264.474809,"iterationCount":215},"tableDone":false},{"tableIndex":0,"percentComplete":0,"currentRowIndex":0,"tableDone":false,"odColumnHeader":{"loss":7.641660213470459,"elapsedTime":2289.130334,"iterationCount":216},"isLast":false,"count":216},{"tableDone":false,"count":217,"tableIndex":0,"percentComplete":0,"odColumnHeader":{"loss":7.6220173835754395,"iterationCount":217,"elapsedTime":2301.015143},"isLast":false,"currentRowIndex":0},{"tableDone":false,"currentRowIndex":0,"percentComplete":0,"odColumnHeader":{"iterationCount":218,"elapsedTime":2313.211316,"loss":7.609832763671875},"tableIndex":0,"isLast":false,"count":218},{"tableIndex":0,"currentRowIndex":0,"tableDone":false,"isLast":false,"percentComplete":0,"count":219,"odColumnHeader":{"loss":7.574038028717041,"elapsedTime":2325.188001,"iterationCount":219}},{"count":220,"isLast":false,"tableDone":false,"percentComplete":0,"currentRowIndex":0,"odColumnHeader":{"iterationCount":220,"loss":7.515582084655762,"elapsedTime":0},"tableIndex":0},{"currentRowIndex":0,"tableIndex":0,"count":221,"odColumnHeader":{"iterationCount":221,"loss":7.5073652267456055,"elapsedTime":2351.032374},"isLast":false,"percentComplete":0,"tableDone":false},{"isLast":false,"tableIndex":0,"count":222,"currentRowIndex":0,"tableDone":false,"percentComplete":0,"odColumnHeader":{"iterationCount":222,"loss":7.5086822509765625,"elapsedTime":2363.731267}},{"tableDone":false,"odColumnHeader":{"loss":7.450223922729492,"iterationCount":223,"elapsedTime":2376.203328},"tableIndex":0,"count":223,"isLast":false,"percentComplete":0,"currentRowIndex":0},{"percentComplete":0,"odColumnHeader":{"loss":7.42826509475708,"iterationCount":224,"elapsedTime":2387.969606},"tableDone":false,"currentRowIndex":0,"tableIndex":0,"isLast":false,"count":224},{"tableDone":false,"percentComplete":0,"currentRowIndex":0,"isLast":false,"count":225,"odColumnHeader":{"elapsedTime":2387.970099,"iterationCount":225,"loss":7.4351582527160645},"tableIndex":0},{"percentComplete":0,"count":226,"isLast":false,"tableDone":false,"currentRowIndex":0,"tableIndex":0,"odColumnHeader":{"loss":7.468841552734375,"elapsedTime":2412.938941,"iterationCount":226}},{"count":227,"tableIndex":0,"tableDone":false,"odColumnHeader":{"iterationCount":227,"loss":7.449012756347656,"elapsedTime":2427.790042},"isLast":false,"currentRowIndex":0,"percentComplete":0},{"odColumnHeader":{"iterationCount":228,"elapsedTime":2440.292215,"loss":7.386178016662598},"tableDone":false,"count":228,"isLast":false,"currentRowIndex":0,"percentComplete":0,"tableIndex":0},{"isLast":false,"tableIndex":0,"percentComplete":0,"currentRowIndex":0,"count":229,"odColumnHeader":{"elapsedTime":2452.158527,"loss":7.3711748123168945,"iterationCount":229},"tableDone":false},{"odColumnHeader":{"iterationCount":230,"loss":7.327673435211182,"elapsedTime":0},"isLast":false,"currentRowIndex":0,"tableIndex":0,"percentComplete":0,"count":230,"tableDone":false},{"count":231,"tableDone":false,"odColumnHeader":{"loss":7.304006099700928,"elapsedTime":2477.956727,"iterationCount":231},"tableIndex":0,"currentRowIndex":0,"percentComplete":0,"isLast":false},{"tableDone":false,"percentComplete":0,"odColumnHeader":{"loss":7.238361358642578,"elapsedTime":2492.262488,"iterationCount":232},"tableIndex":0,"isLast":false,"count":232,"currentRowIndex":0},{"count":233,"currentRowIndex":0,"percentComplete":0,"isLast":false,"tableDone":false,"tableIndex":0,"odColumnHeader":{"iterationCount":233,"loss":7.187729835510254,"elapsedTime":2506.565496}},{"tableDone":false,"count":234,"odColumnHeader":{"loss":7.177043437957764,"elapsedTime":2519.350444,"iterationCount":234},"currentRowIndex":0,"isLast":false,"tableIndex":0,"percentComplete":0},{"odColumnHeader":{"iterationCount":235,"loss":7.176275730133057,"elapsedTime":2519.352849},"tableIndex":0,"percentComplete":0,"isLast":false,"currentRowIndex":0,"count":235,"tableDone":false},{"odColumnHeader":{"iterationCount":236,"loss":7.149764060974121,"elapsedTime":2544.884187},"count":236,"currentRowIndex":0,"tableDone":false,"percentComplete":0,"tableIndex":0,"isLast":false},{"count":237,"isLast":false,"odColumnHeader":{"elapsedTime":2556.936398,"loss":7.153492450714111,"iterationCount":237},"percentComplete":0,"tableIndex":0,"tableDone":false,"currentRowIndex":0},{"tableDone":false,"currentRowIndex":0,"tableIndex":0,"isLast":false,"count":238,"percentComplete":0,"odColumnHeader":{"iterationCount":238,"loss":7.132184982299805,"elapsedTime":2569.136274}},{"tableIndex":0,"isLast":false,"odColumnHeader":{"loss":7.139692306518555,"elapsedTime":2581.559845,"iterationCount":239},"currentRowIndex":0,"tableDone":false,"percentComplete":0,"count":239},{"isLast":false,"count":240,"tableDone":false,"tableIndex":0,"currentRowIndex":0,"percentComplete":0,"odColumnHeader":{"loss":7.20644474029541,"elapsedTime":0,"iterationCount":240}},{"isLast":false,"tableIndex":0,"count":241,"percentComplete":0,"tableDone":false,"odColumnHeader":{"elapsedTime":2608.905678,"iterationCount":241,"loss":7.165245056152344},"currentRowIndex":0},{"percentComplete":0,"isLast":false,"tableDone":false,"count":242,"currentRowIndex":0,"odColumnHeader":{"iterationCount":242,"loss":7.156922817230225,"elapsedTime":2620.408163},"tableIndex":0},{"count":243,"tableDone":false,"odColumnHeader":{"iterationCount":243,"elapsedTime":2634.636792,"loss":7.103335857391357},"isLast":false,"tableIndex":0,"percentComplete":0,"currentRowIndex":0},{"tableDone":false,"count":244,"currentRowIndex":0,"isLast":false,"tableIndex":0,"percentComplete":0,"odColumnHeader":{"elapsedTime":2650.536809,"iterationCount":244,"loss":7.067990779876709}},{"currentRowIndex":0,"odColumnHeader":{"iterationCount":245,"loss":7.090121269226074,"elapsedTime":2650.537172},"tableDone":false,"isLast":false,"percentComplete":0,"tableIndex":0,"count":245},{"tableIndex":0,"count":246,"percentComplete":0,"currentRowIndex":0,"odColumnHeader":{"elapsedTime":2678.585567,"iterationCount":246,"loss":7.090928554534912},"isLast":false,"tableDone":false},{"count":247,"percentComplete":0,"tableIndex":0,"tableDone":false,"isLast":false,"currentRowIndex":0,"odColumnHeader":{"elapsedTime":2690.854889,"iterationCount":247,"loss":7.051586627960205}},{"isLast":false,"tableDone":false,"currentRowIndex":0,"percentComplete":0,"tableIndex":0,"odColumnHeader":{"iterationCount":248,"loss":7.015949726104736,"elapsedTime":2704.194166},"count":248},{"isLast":false,"odColumnHeader":{"loss":6.9793267250061035,"iterationCount":249,"elapsedTime":2717.716761},"tableIndex":0,"tableDone":false,"count":249,"percentComplete":0,"currentRowIndex":0},{"currentRowIndex":0,"odColumnHeader":{"iterationCount":250,"loss":6.993838787078857,"elapsedTime":0},"isLast":false,"tableDone":false,"tableIndex":0,"percentComplete":0,"count":250},{"tableDone":false,"currentRowIndex":0,"isLast":false,"count":251,"odColumnHeader":{"elapsedTime":2744.997623,"iterationCount":251,"loss":7.0039849281311035},"percentComplete":0,"tableIndex":0},{"tableIndex":0,"isLast":false,"percentComplete":0,"count":252,"tableDone":false,"currentRowIndex":0,"odColumnHeader":{"elapsedTime":2758.056661,"iterationCount":252,"loss":7.015087127685547}},{"odColumnHeader":{"loss":7.0265021324157715,"elapsedTime":2770.406801,"iterationCount":253},"tableIndex":0,"tableDone":false,"currentRowIndex":0,"percentComplete":0,"count":253,"isLast":false},{"percentComplete":0,"isLast":false,"tableDone":false,"count":254,"odColumnHeader":{"iterationCount":254,"loss":6.99474573135376,"elapsedTime":2783.74669},"tableIndex":0,"currentRowIndex":0},{"currentRowIndex":0,"odColumnHeader":{"iterationCount":255,"elapsedTime":2783.747282,"loss":6.996542453765869},"tableDone":false,"isLast":false,"percentComplete":0,"count":255,"tableIndex":0},{"currentRowIndex":0,"isLast":false,"tableDone":false,"percentComplete":0,"odColumnHeader":{"iterationCount":256,"elapsedTime":2809.089026,"loss":6.915480136871338},"tableIndex":0,"count":256},{"odColumnHeader":{"elapsedTime":2821.258735,"iterationCount":257,"loss":6.918654441833496},"currentRowIndex":0,"tableDone":false,"percentComplete":0,"tableIndex":0,"isLast":false,"count":257},{"odColumnHeader":{"iterationCount":258,"elapsedTime":2833.417664,"loss":6.853533744812012},"isLast":false,"tableDone":false,"percentComplete":0,"currentRowIndex":0,"count":258,"tableIndex":0},{"tableIndex":0,"odColumnHeader":{"elapsedTime":2845.558121,"loss":6.840101718902588,"iterationCount":259},"percentComplete":0,"tableDone":false,"currentRowIndex":0,"isLast":false,"count":259},{"count":260,"tableIndex":0,"tableDone":false,"currentRowIndex":0,"percentComplete":0,"isLast":false,"odColumnHeader":{"iterationCount":260,"loss":6.870141506195068,"elapsedTime":0}},{"currentRowIndex":0,"isLast":false,"percentComplete":0,"count":261,"tableDone":false,"tableIndex":0,"odColumnHeader":{"loss":6.896975994110107,"elapsedTime":2871.03903,"iterationCount":261}},{"count":262,"odColumnHeader":{"loss":6.915104866027832,"iterationCount":262,"elapsedTime":2883.003418},"tableDone":false,"percentComplete":0,"isLast":false,"tableIndex":0,"currentRowIndex":0},{"tableDone":false,"currentRowIndex":0,"percentComplete":0,"odColumnHeader":{"loss":6.916168212890625,"elapsedTime":2895.226902,"iterationCount":263},"tableIndex":0,"isLast":false,"count":263},{"isLast":false,"tableDone":false,"currentRowIndex":0,"tableIndex":0,"count":264,"percentComplete":0,"odColumnHeader":{"iterationCount":264,"elapsedTime":2908.023917,"loss":6.945959091186523}},{"tableIndex":0,"isLast":false,"currentRowIndex":0,"tableDone":false,"count":265,"percentComplete":0,"odColumnHeader":{"iterationCount":265,"elapsedTime":2908.024301,"loss":7.013186454772949}},{"count":266,"odColumnHeader":{"iterationCount":266,"loss":7.0305256843566895,"elapsedTime":2931.812685},"tableIndex":0,"tableDone":false,"currentRowIndex":0,"isLast":false,"percentComplete":0},{"isLast":false,"count":267,"tableIndex":0,"odColumnHeader":{"iterationCount":267,"elapsedTime":2944.108595,"loss":7.071547985076904},"tableDone":false,"percentComplete":0,"currentRowIndex":0},{"percentComplete":0,"odColumnHeader":{"elapsedTime":2957.813261,"loss":7.059373378753662,"iterationCount":268},"currentRowIndex":0,"tableDone":false,"isLast":false,"count":268,"tableIndex":0},{"odColumnHeader":{"loss":7.0538458824157715,"elapsedTime":2969.916514,"iterationCount":269},"tableIndex":0,"tableDone":false,"currentRowIndex":0,"count":269,"isLast":false,"percentComplete":0},{"tableIndex":0,"currentRowIndex":0,"isLast":false,"tableDone":false,"percentComplete":0,"count":270,"odColumnHeader":{"iterationCount":270,"elapsedTime":0,"loss":7.033077239990234}},{"currentRowIndex":0,"tableIndex":0,"percentComplete":0,"odColumnHeader":{"elapsedTime":2995.367112,"loss":7.034852504730225,"iterationCount":271},"tableDone":false,"count":271,"isLast":false},{"percentComplete":0,"tableIndex":0,"odColumnHeader":{"iterationCount":272,"elapsedTime":3007.222497,"loss":7.015593528747559},"tableDone":false,"isLast":false,"currentRowIndex":0,"count":272},{"tableIndex":0,"count":273,"percentComplete":0,"currentRowIndex":0,"odColumnHeader":{"loss":6.954763889312744,"elapsedTime":3019.328111,"iterationCount":273},"tableDone":false,"isLast":false},{"odColumnHeader":{"loss":6.959522724151611,"elapsedTime":3031.557119,"iterationCount":274},"currentRowIndex":0,"tableIndex":0,"tableDone":false,"isLast":false,"count":274,"percentComplete":0},{"tableIndex":0,"percentComplete":0,"odColumnHeader":{"elapsedTime":3031.557359,"iterationCount":275,"loss":6.954474925994873},"count":275,"currentRowIndex":0,"tableDone":false,"isLast":false},{"currentRowIndex":0,"percentComplete":0,"count":276,"odColumnHeader":{"iterationCount":276,"loss":7.016141414642334,"elapsedTime":3057.963243},"tableIndex":0,"isLast":false,"tableDone":false},{"isLast":false,"percentComplete":0,"count":277,"currentRowIndex":0,"tableIndex":0,"odColumnHeader":{"loss":7.04664945602417,"elapsedTime":3070.965965,"iterationCount":277},"tableDone":false},{"isLast":false,"odColumnHeader":{"iterationCount":278,"loss":6.969346523284912,"elapsedTime":3084.100765},"tableDone":false,"currentRowIndex":0,"percentComplete":0,"tableIndex":0,"count":278},{"currentRowIndex":0,"percentComplete":0,"tableIndex":0,"isLast":false,"count":279,"odColumnHeader":{"loss":6.964561939239502,"iterationCount":279,"elapsedTime":3095.991792},"tableDone":false},{"count":280,"isLast":false,"tableDone":false,"tableIndex":0,"currentRowIndex":0,"percentComplete":0,"odColumnHeader":{"iterationCount":280,"loss":6.914895057678223,"elapsedTime":0}},{"odColumnHeader":{"elapsedTime":3121.28503,"loss":6.925631999969482,"iterationCount":281},"tableIndex":0,"tableDone":false,"currentRowIndex":0,"isLast":false,"count":281,"percentComplete":0},{"count":282,"percentComplete":0,"odColumnHeader":{"loss":6.881345748901367,"elapsedTime":3132.946232,"iterationCount":282},"tableDone":false,"currentRowIndex":0,"isLast":false,"tableIndex":0},{"percentComplete":0,"count":283,"odColumnHeader":{"iterationCount":283,"loss":6.8406662940979,"elapsedTime":3147.907033},"isLast":false,"tableDone":false,"tableIndex":0,"currentRowIndex":0},{"odColumnHeader":{"iterationCount":284,"elapsedTime":3159.865362,"loss":6.862221717834473},"currentRowIndex":0,"isLast":false,"count":284,"tableIndex":0,"percentComplete":0,"tableDone":false},{"isLast":false,"currentRowIndex":0,"percentComplete":0,"odColumnHeader":{"loss":6.866057395935059,"elapsedTime":3159.865655,"iterationCount":285},"tableDone":false,"tableIndex":0,"count":285},{"currentRowIndex":0,"percentComplete":0,"tableDone":false,"isLast":false,"odColumnHeader":{"iterationCount":286,"loss":6.828036785125732,"elapsedTime":3183.842979},"count":286,"tableIndex":0},{"odColumnHeader":{"iterationCount":287,"elapsedTime":3196.055558,"loss":6.848958969116211},"currentRowIndex":0,"tableIndex":0,"tableDone":false,"isLast":false,"percentComplete":0,"count":287},{"count":288,"tableDone":false,"currentRowIndex":0,"odColumnHeader":{"elapsedTime":3208.279509,"iterationCount":288,"loss":6.831925868988037},"isLast":false,"tableIndex":0,"percentComplete":0},{"isLast":false,"odColumnHeader":{"loss":6.832794189453125,"elapsedTime":3220.092149,"iterationCount":289},"tableIndex":0,"currentRowIndex":0,"percentComplete":0,"tableDone":false,"count":289},{"percentComplete":0,"odColumnHeader":{"iterationCount":290,"elapsedTime":0,"loss":6.814861297607422},"tableDone":false,"count":290,"tableIndex":0,"currentRowIndex":0,"isLast":false},{"tableDone":false,"currentRowIndex":0,"tableIndex":0,"count":291,"percentComplete":0,"isLast":false,"odColumnHeader":{"iterationCount":291,"loss":6.825916290283203,"elapsedTime":3248.437469}},{"percentComplete":0,"isLast":false,"count":292,"currentRowIndex":0,"odColumnHeader":{"iterationCount":292,"loss":6.73524284362793,"elapsedTime":3262.908293},"tableDone":false,"tableIndex":0},{"currentRowIndex":0,"odColumnHeader":{"loss":6.66570520401001,"iterationCount":293,"elapsedTime":3277.483458},"count":293,"percentComplete":0,"tableIndex":0,"tableDone":false,"isLast":false},{"percentComplete":0,"tableIndex":0,"isLast":false,"tableDone":false,"odColumnHeader":{"iterationCount":294,"loss":6.671448230743408,"elapsedTime":3289.813344},"count":294,"currentRowIndex":0},{"percentComplete":0,"tableIndex":0,"currentRowIndex":0,"odColumnHeader":{"loss":6.6722540855407715,"iterationCount":295,"elapsedTime":3289.813715},"isLast":false,"count":295,"tableDone":false},{"count":296,"tableIndex":0,"odColumnHeader":{"iterationCount":296,"loss":6.59832763671875,"elapsedTime":3318.653863},"tableDone":false,"percentComplete":0,"currentRowIndex":0,"isLast":false},{"count":297,"odColumnHeader":{"elapsedTime":3331.265129,"loss":6.620121002197266,"iterationCount":297},"percentComplete":0,"tableIndex":0,"tableDone":false,"currentRowIndex":0,"isLast":false},{"tableIndex":0,"currentRowIndex":0,"percentComplete":0,"odColumnHeader":{"iterationCount":298,"loss":6.570252418518066,"elapsedTime":3343.570171},"isLast":false,"tableDone":false,"count":298},{"tableDone":false,"percentComplete":0,"odColumnHeader":{"iterationCount":299,"loss":6.610889434814453,"elapsedTime":3355.774845},"tableIndex":0,"currentRowIndex":0,"count":299,"isLast":false},{"percentComplete":0,"odColumnHeader":{"elapsedTime":0,"loss":6.647951126098633,"iterationCount":300},"tableDone":false,"isLast":false,"count":300,"tableIndex":0,"currentRowIndex":0},{"tableIndex":0,"odColumnHeader":{"loss":6.640097618103027,"iterationCount":301,"elapsedTime":3381.249905},"tableDone":false,"isLast":false,"count":301,"currentRowIndex":0,"percentComplete":0},{"tableIndex":0,"tableDone":false,"currentRowIndex":0,"odColumnHeader":{"iterationCount":302,"loss":6.606052398681641,"elapsedTime":3393.024491},"count":302,"percentComplete":0,"isLast":false},{"isLast":false,"odColumnHeader":{"iterationCount":303,"elapsedTime":3404.697193,"loss":6.588998317718506},"tableIndex":0,"percentComplete":0,"currentRowIndex":0,"tableDone":false,"count":303},{"tableDone":false,"count":304,"percentComplete":0,"currentRowIndex":0,"isLast":false,"tableIndex":0,"odColumnHeader":{"iterationCount":304,"loss":6.594513416290283,"elapsedTime":3416.689497}},{"tableIndex":0,"percentComplete":0,"odColumnHeader":{"loss":6.626494884490967,"elapsedTime":3416.689879,"iterationCount":305},"isLast":false,"count":305,"currentRowIndex":0,"tableDone":false},{"count":306,"odColumnHeader":{"iterationCount":306,"elapsedTime":3442.619178,"loss":6.5764899253845215},"tableDone":false,"tableIndex":0,"percentComplete":0,"currentRowIndex":0,"isLast":false},{"tableDone":false,"currentRowIndex":0,"percentComplete":0,"tableIndex":0,"odColumnHeader":{"loss":6.542236804962158,"elapsedTime":3456.212047,"iterationCount":307},"isLast":false,"count":307},{"count":308,"odColumnHeader":{"elapsedTime":3468.310375,"iterationCount":308,"loss":6.543045520782471},"currentRowIndex":0,"percentComplete":0,"tableDone":false,"isLast":false,"tableIndex":0},{"odColumnHeader":{"elapsedTime":3480.358641,"loss":6.475640296936035,"iterationCount":309},"tableDone":false,"count":309,"isLast":false,"currentRowIndex":0,"percentComplete":0,"tableIndex":0},{"percentComplete":0,"tableDone":false,"count":310,"isLast":false,"currentRowIndex":0,"odColumnHeader":{"loss":6.489870548248291,"iterationCount":310,"elapsedTime":0},"tableIndex":0},{"tableIndex":0,"currentRowIndex":0,"count":311,"isLast":false,"tableDone":false,"odColumnHeader":{"iterationCount":311,"loss":6.512264728546143,"elapsedTime":3506.933533},"percentComplete":0},{"isLast":false,"tableIndex":0,"currentRowIndex":0,"tableDone":false,"count":312,"odColumnHeader":{"iterationCount":312,"loss":6.539412975311279,"elapsedTime":3519.301227},"percentComplete":0},{"count":313,"currentRowIndex":0,"isLast":false,"tableDone":false,"tableIndex":0,"percentComplete":0,"odColumnHeader":{"iterationCount":313,"elapsedTime":3531.548721,"loss":6.557380676269531}},{"currentRowIndex":0,"isLast":false,"percentComplete":0,"odColumnHeader":{"loss":6.528213977813721,"elapsedTime":3543.969123,"iterationCount":314},"count":314,"tableDone":false,"tableIndex":0},{"tableIndex":0,"tableDone":false,"isLast":false,"percentComplete":0,"currentRowIndex":0,"count":315,"odColumnHeader":{"loss":6.521682262420654,"elapsedTime":3543.969451,"iterationCount":315}},{"odColumnHeader":{"loss":6.517726421356201,"iterationCount":316,"elapsedTime":3571.973925},"tableIndex":0,"isLast":false,"currentRowIndex":0,"tableDone":false,"percentComplete":0,"count":316},{"tableDone":false,"count":317,"isLast":false,"currentRowIndex":0,"tableIndex":0,"odColumnHeader":{"loss":6.50111722946167,"elapsedTime":3592.27587,"iterationCount":317},"percentComplete":0},{"isLast":false,"currentRowIndex":0,"count":318,"percentComplete":0,"tableDone":false,"odColumnHeader":{"elapsedTime":3606.950744,"iterationCount":318,"loss":6.5087714195251465},"tableIndex":0},{"percentComplete":0,"count":319,"tableIndex":0,"tableDone":false,"currentRowIndex":0,"isLast":false,"odColumnHeader":{"iterationCount":319,"loss":6.505649089813232,"elapsedTime":3625.80453}},{"currentRowIndex":0,"tableIndex":0,"isLast":false,"count":320,"percentComplete":0,"tableDone":false,"odColumnHeader":{"loss":6.466634273529053,"iterationCount":320,"elapsedTime":0}},{"isLast":false,"tableIndex":0,"currentRowIndex":0,"odColumnHeader":{"elapsedTime":29.411394,"iterationCount":321,"loss":6.454330921173096},"tableDone":false,"percentComplete":0,"count":321},{"currentRowIndex":0,"count":322,"odColumnHeader":{"loss":6.4546122550964355,"elapsedTime":41.538421,"iterationCount":322},"percentComplete":0,"tableDone":false,"tableIndex":0,"isLast":false},{"currentRowIndex":0,"tableIndex":0,"percentComplete":0,"isLast":false,"count":323,"odColumnHeader":{"elapsedTime":54.036695,"iterationCount":323,"loss":6.466890335083008},"tableDone":false},{"odColumnHeader":{"iterationCount":324,"elapsedTime":66.03766,"loss":6.440576553344727},"tableIndex":0,"count":324,"currentRowIndex":0,"isLast":false,"percentComplete":0,"tableDone":false},{"tableIndex":0,"percentComplete":0,"odColumnHeader":{"elapsedTime":66.038014,"iterationCount":325,"loss":6.455810546875},"isLast":false,"currentRowIndex":0,"tableDone":false,"count":325},{"tableIndex":0,"count":327,"currentRowIndex":0,"percentComplete":0,"odColumnHeader":{"elapsedTime":103.391459,"loss":6.436077117919922,"iterationCount":327},"tableDone":false,"isLast":false},{"count":328,"tableIndex":0,"isLast":false,"odColumnHeader":{"loss":6.404168128967285,"elapsedTime":116.060232,"iterationCount":328},"currentRowIndex":0,"tableDone":false,"percentComplete":0},{"percentComplete":0,"count":329,"tableDone":false,"isLast":false,"odColumnHeader":{"elapsedTime":128.00447,"iterationCount":329,"loss":6.363129615783691},"currentRowIndex":0,"tableIndex":0},{"isLast":false,"count":330,"percentComplete":0,"tableDone":false,"odColumnHeader":{"elapsedTime":0,"loss":6.413157939910889,"iterationCount":330},"tableIndex":0,"currentRowIndex":0},{"currentRowIndex":0,"tableIndex":0,"tableDone":false,"isLast":false,"count":331,"percentComplete":0,"odColumnHeader":{"iterationCount":331,"elapsedTime":158.459991,"loss":6.411555767059326}},{"odColumnHeader":{"loss":6.365316390991211,"elapsedTime":172.837797,"iterationCount":332},"tableDone":false,"tableIndex":0,"count":332,"isLast":false,"percentComplete":0,"currentRowIndex":0},{"count":333,"odColumnHeader":{"elapsedTime":185.281637,"loss":6.325244426727295,"iterationCount":333},"isLast":false,"percentComplete":0,"tableDone":false,"tableIndex":0,"currentRowIndex":0},{"odColumnHeader":{"loss":6.33665132522583,"iterationCount":334,"elapsedTime":201.536629},"count":334,"isLast":false,"currentRowIndex":0,"tableDone":false,"tableIndex":0,"percentComplete":0},{"count":335,"tableIndex":0,"percentComplete":0,"currentRowIndex":0,"tableDone":false,"isLast":false,"odColumnHeader":{"iterationCount":335,"loss":6.320138454437256,"elapsedTime":201.537132}},{"percentComplete":0,"count":336,"tableIndex":0,"odColumnHeader":{"iterationCount":336,"loss":6.314476490020752,"elapsedTime":230.38493},"isLast":false,"tableDone":false,"currentRowIndex":0},{"percentComplete":0,"tableDone":false,"tableIndex":0,"currentRowIndex":0,"odColumnHeader":{"elapsedTime":249.08002,"iterationCount":337,"loss":6.300049781799316},"count":337,"isLast":false},{"tableDone":false,"tableIndex":0,"currentRowIndex":0,"isLast":false,"count":338,"percentComplete":0,"odColumnHeader":{"loss":6.333854675292969,"elapsedTime":278.455676,"iterationCount":338}},{"currentRowIndex":0,"tableDone":false,"count":339,"percentComplete":0,"isLast":false,"odColumnHeader":{"loss":6.403653621673584,"elapsedTime":290.286543,"iterationCount":339},"tableIndex":0},{"tableIndex":0,"odColumnHeader":{"iterationCount":340,"loss":6.409465789794922,"elapsedTime":0},"currentRowIndex":0,"isLast":false,"percentComplete":0,"tableDone":false,"count":340}],"snapshottableCheckpointModelURL":"Checkpoints\/0DF2994C-AFB3-4B23-A36B-CB166D1F486E.scrabbleDetectorWithRotation2copy2.checkpoint\/training-000000340.checkpoint.model\/checkpointModel.mlmodel","error":{"domain":"composer.error.domain","code":1004,"errorType":"info","reason":"Training Stopped"},"checkpointMetrics":{"250":{"metrics":{"loss":6.993838787078857},"createdDate":"2024-11-12T21:55:48Z","iteration":250},"220":{"createdDate":"2024-11-12T21:49:16Z","iteration":220,"metrics":{"loss":7.515582084655762}},"190":{"iteration":190,"metrics":{"loss":8.043646812438965},"createdDate":"2024-11-12T21:42:53Z"},"10":{"metrics":{"loss":23.45566177368164},"createdDate":"2024-11-08T21:50:22Z","iteration":10},"20":{"createdDate":"2024-11-08T21:52:39Z","metrics":{"loss":20.85234260559082},"iteration":20},"290":{"metrics":{"loss":6.814861297607422},"iteration":290,"createdDate":"2024-11-12T22:04:11Z"},"320":{"iteration":320,"createdDate":"2024-11-12T22:10:56Z","metrics":{"loss":6.466634273529053}},"110":{"iteration":110,"metrics":{"loss":10.535685539245605},"createdDate":"2024-11-12T21:25:39Z"},"40":{"metrics":{"loss":14.772141456604004},"createdDate":"2024-11-08T21:58:50Z","iteration":40},"310":{"metrics":{"loss":6.489870548248291},"iteration":310,"createdDate":"2024-11-12T22:08:31Z"},"340":{"createdDate":"2024-11-12T22:27:10Z","metrics":{"loss":6.409465789794922},"iteration":340},"210":{"metrics":{"loss":7.583600997924805},"iteration":210,"createdDate":"2024-11-12T21:47:13Z"},"60":{"iteration":60,"metrics":{"loss":12.863679885864258},"createdDate":"2024-11-12T21:14:43Z"},"330":{"metrics":{"loss":6.413157939910889},"iteration":330,"createdDate":"2024-11-12T22:24:28Z"},"280":{"iteration":280,"metrics":{"loss":6.914895057678223},"createdDate":"2024-11-12T22:02:07Z"},"80":{"metrics":{"loss":11.715408325195312},"iteration":80,"createdDate":"2024-11-12T21:19:09Z"},"230":{"createdDate":"2024-11-12T21:51:23Z","iteration":230,"metrics":{"loss":7.327673435211182}},"270":{"metrics":{"loss":7.033077239990234},"createdDate":"2024-11-12T22:00:01Z","iteration":270},"70":{"metrics":{"loss":12.174627304077148},"iteration":70,"createdDate":"2024-11-12T21:16:58Z"},"240":{"createdDate":"2024-11-12T21:53:32Z","iteration":240,"metrics":{"loss":7.20644474029541}},"150":{"iteration":150,"metrics":{"loss":9.05312442779541},"createdDate":"2024-11-12T21:34:24Z"},"140":{"iteration":140,"metrics":{"loss":9.420677185058594},"createdDate":"2024-11-12T21:32:09Z"},"170":{"iteration":170,"metrics":{"loss":8.487889289855957},"createdDate":"2024-11-12T21:38:46Z"},"90":{"iteration":90,"metrics":{"loss":11.182943344116211},"createdDate":"2024-11-12T21:21:23Z"},"160":{"createdDate":"2024-11-12T21:36:42Z","iteration":160,"metrics":{"loss":8.762304306030273}},"120":{"createdDate":"2024-11-12T21:27:47Z","iteration":120,"metrics":{"loss":10.075236320495605}},"300":{"createdDate":"2024-11-12T22:06:26Z","metrics":{"loss":6.647951126098633},"iteration":300},"50":{"iteration":50,"metrics":{"loss":13.58350944519043},"createdDate":"2024-11-12T21:12:36Z"},"180":{"metrics":{"loss":8.20540714263916},"createdDate":"2024-11-12T21:40:47Z","iteration":180},"260":{"iteration":260,"metrics":{"loss":6.870141506195068},"createdDate":"2024-11-12T21:57:56Z"},"30":{"createdDate":"2024-11-08T21:55:41Z","iteration":30,"metrics":{"loss":17.045469284057617}},"200":{"createdDate":"2024-11-12T21:45:06Z","iteration":200,"metrics":{"loss":7.862246513366699}},"100":{"iteration":100,"createdDate":"2024-11-12T21:23:33Z","metrics":{"loss":10.835480690002441}},"130":{"metrics":{"loss":9.811863899230957},"iteration":130,"createdDate":"2024-11-12T21:29:50Z"}},"featureExtractionCheckpointMayBeAvailable":false,"resumableCheckpoint":{"iteration":340,"createdDate":"2024-11-12T22:27:10Z","checkpointURL":"file:\/\/\/Users\/teerthrajparmar\/Library\/Caches\/com.apple.dt.createml\/projects\/EB82AE05-2BC3-4BCF-94A7-5AD7AFF1B32233968d2ea6edb189a466bbfab88d829d1c8088a7\/sessions\/checkpoint.sessions\/0DF2994C-AFB3-4B23-A36B-CB166D1F486E\/training-000000340.checkpoint"}}}