{"title":"Iteration 610","modifiedDate":"2024-11-01T20:41:29Z","preferredFilename":"ScrabbleDetectorWithRotation 2 Iteration 610","evaluationState":"evaluated","modelEntity":{"experimentID":"760DAA1F-53F5-4198-B2A9-D6A73D4D10C7","createdDate":"2024-11-01T20:30:48Z","preferredFilename":"","modifiedDate":"2024-11-01T20:30:48Z","id":"8AD3CF9E-DA3F-4418-89AB-54499529CBA8","version":"1.0","modelURL":"Snapshots\/ScrabbleDetectorWithRotation%202%20Iteration%20610.mlmodel","title":""},"trainingEntity":{"resumableCheckpoint":{"iteration":610,"createdDate":"2024-11-01T20:30:47Z","checkpointURL":"file:\/\/\/Users\/teerthrajparmar\/Library\/Caches\/com.apple.dt.createml\/projects\/EB82AE05-2BC3-4BCF-94A7-5AD7AFF1B32233968d2ea6edb189a466bbfab88d829d1c8088a7\/sessions\/checkpoint.sessions\/760DAA1F-53F5-4198-B2A9-D6A73D4D10C7\/training-000000610.checkpoint"},"dataSourceID":"49E1FB54-40D0-4E54-8FF6-4B6AF3BC6C75","dataResult":{"itemsCount":48,"dataURL":"file:\/\/\/Users\/teerthrajparmar\/development\/BoardSolverData\/finalRotatedImages\/train\/","dataSourceID":"49E1FB54-40D0-4E54-8FF6-4B6AF3BC6C75","dataAnalysis":{"summary":{"classCount":28,"sampleCount":48,"suggestedMaxIterations":17000,"counterExamples":0,"canUseValidation":1},"classifierAnalysis":{},"objectDetectorAnalysis":{"labelStats":{"I":270,"O":180,"T":129,"K":42,"C":51,"M":96,"Y":42,"Z":45,"F":42,"R":174,"N":144,"V":75,"D":96,"J":36,"E":264,"X":51,"P":84,"L":132,"H":81,"W":75,"U":144,"B":57,"S":81,"Q":39,"A":276,"Blank":45,"G":60,"Board":48},"details":{}},"issues":[{"severity":"debug","description":"28 classes found, including A, I, E"},{"description":"Less than 50 total images found - add more to improve model validation","severity":"warning"},{"description":"Smallest class is \"J\" with 36 images","severity":"debug"},{"severity":"debug","description":"Largest class is \"A\" with 276 images"}]},"classesCount":28,"createdDate":"2024-11-01T20:30:48Z"},"startTime":"2024-11-01T20:22:23Z","checkpointMetrics":{"320":{"iteration":320,"metrics":{"loss":16.467905044555664},"createdDate":"2024-11-01T20:26:45Z"},"360":{"metrics":{"loss":16.25139617919922},"createdDate":"2024-11-01T20:27:17Z","iteration":360},"540":{"metrics":{"loss":15.98532485961914},"iteration":540,"createdDate":"2024-11-01T20:29:49Z"},"200":{"createdDate":"2024-11-01T20:25:08Z","metrics":{"loss":16.406694412231445},"iteration":200},"20":{"metrics":{"loss":25.561264038085938},"iteration":20,"createdDate":"2024-11-01T20:22:41Z"},"130":{"createdDate":"2024-11-01T20:24:09Z","iteration":130,"metrics":{"loss":16.38890266418457}},"310":{"createdDate":"2024-11-01T20:26:37Z","metrics":{"loss":16.622474670410156},"iteration":310},"490":{"metrics":{"loss":16.282581329345703},"createdDate":"2024-11-01T20:29:06Z","iteration":490},"470":{"metrics":{"loss":16.223344802856445},"iteration":470,"createdDate":"2024-11-01T20:28:50Z"},"350":{"iteration":350,"createdDate":"2024-11-01T20:27:09Z","metrics":{"loss":16.155139923095703}},"410":{"createdDate":"2024-11-01T20:27:59Z","metrics":{"loss":16.34536361694336},"iteration":410},"390":{"iteration":390,"metrics":{"loss":16.27922248840332},"createdDate":"2024-11-01T20:27:42Z"},"560":{"iteration":560,"createdDate":"2024-11-01T20:30:06Z","metrics":{"loss":16.156625747680664}},"340":{"metrics":{"loss":16.258331298828125},"createdDate":"2024-11-01T20:27:01Z","iteration":340},"170":{"createdDate":"2024-11-01T20:24:42Z","iteration":170,"metrics":{"loss":16.413734436035156}},"570":{"iteration":570,"metrics":{"loss":16.239961624145508},"createdDate":"2024-11-01T20:30:15Z"},"520":{"iteration":520,"createdDate":"2024-11-01T20:29:31Z","metrics":{"loss":16.070953369140625}},"480":{"iteration":480,"metrics":{"loss":16.18989372253418},"createdDate":"2024-11-01T20:28:58Z"},"140":{"metrics":{"loss":16.625226974487305},"createdDate":"2024-11-01T20:24:18Z","iteration":140},"330":{"metrics":{"loss":16.493227005004883},"createdDate":"2024-11-01T20:26:53Z","iteration":330},"90":{"createdDate":"2024-11-01T20:23:37Z","iteration":90,"metrics":{"loss":16.609691619873047}},"420":{"metrics":{"loss":16.47896957397461},"iteration":420,"createdDate":"2024-11-01T20:28:08Z"},"400":{"metrics":{"loss":16.297212600708008},"createdDate":"2024-11-01T20:27:51Z","iteration":400},"210":{"iteration":210,"metrics":{"loss":16.56757926940918},"createdDate":"2024-11-01T20:25:16Z"},"270":{"metrics":{"loss":16.621126174926758},"createdDate":"2024-11-01T20:26:04Z","iteration":270},"70":{"metrics":{"loss":16.85935401916504},"createdDate":"2024-11-01T20:23:21Z","iteration":70},"580":{"iteration":580,"metrics":{"loss":15.86856746673584},"createdDate":"2024-11-01T20:30:23Z"},"50":{"iteration":50,"metrics":{"loss":17.460372924804688},"createdDate":"2024-11-01T20:23:05Z"},"120":{"metrics":{"loss":16.658288955688477},"createdDate":"2024-11-01T20:24:01Z","iteration":120},"190":{"metrics":{"loss":16.373844146728516},"createdDate":"2024-11-01T20:25:00Z","iteration":190},"230":{"createdDate":"2024-11-01T20:25:32Z","metrics":{"loss":16.599275588989258},"iteration":230},"290":{"metrics":{"loss":16.720428466796875},"iteration":290,"createdDate":"2024-11-01T20:26:21Z"},"60":{"createdDate":"2024-11-01T20:23:13Z","iteration":60,"metrics":{"loss":17.07047462463379}},"610":{"iteration":610,"createdDate":"2024-11-01T20:30:47Z","metrics":{"loss":15.930257797241211}},"100":{"metrics":{"loss":16.61199188232422},"iteration":100,"createdDate":"2024-11-01T20:23:45Z"},"500":{"iteration":500,"metrics":{"loss":16.452993392944336},"createdDate":"2024-11-01T20:29:14Z"},"220":{"createdDate":"2024-11-01T20:25:24Z","iteration":220,"metrics":{"loss":16.627521514892578}},"460":{"metrics":{"loss":16.33327865600586},"createdDate":"2024-11-01T20:28:41Z","iteration":460},"590":{"createdDate":"2024-11-01T20:30:31Z","iteration":590,"metrics":{"loss":15.981330871582031}},"110":{"iteration":110,"metrics":{"loss":16.5277156829834},"createdDate":"2024-11-01T20:23:53Z"},"180":{"iteration":180,"metrics":{"loss":16.58378028869629},"createdDate":"2024-11-01T20:24:51Z"},"530":{"metrics":{"loss":16.089946746826172},"createdDate":"2024-11-01T20:29:40Z","iteration":530},"40":{"metrics":{"loss":18.90729522705078},"createdDate":"2024-11-01T20:22:57Z","iteration":40},"80":{"iteration":80,"metrics":{"loss":16.961244583129883},"createdDate":"2024-11-01T20:23:29Z"},"600":{"createdDate":"2024-11-01T20:30:39Z","iteration":600,"metrics":{"loss":15.928003311157227}},"450":{"metrics":{"loss":16.570432662963867},"createdDate":"2024-11-01T20:28:32Z","iteration":450},"260":{"metrics":{"loss":16.36216926574707},"createdDate":"2024-11-01T20:25:56Z","iteration":260},"280":{"metrics":{"loss":16.573589324951172},"iteration":280,"createdDate":"2024-11-01T20:26:12Z"},"370":{"iteration":370,"createdDate":"2024-11-01T20:27:25Z","metrics":{"loss":16.384326934814453}},"240":{"createdDate":"2024-11-01T20:25:40Z","iteration":240,"metrics":{"loss":16.412261962890625}},"30":{"createdDate":"2024-11-01T20:22:49Z","iteration":30,"metrics":{"loss":21.163982391357422}},"250":{"createdDate":"2024-11-01T20:25:48Z","metrics":{"loss":16.558862686157227},"iteration":250},"300":{"iteration":300,"metrics":{"loss":16.87462615966797},"createdDate":"2024-11-01T20:26:29Z"},"10":{"metrics":{"loss":33.10317611694336},"iteration":10,"createdDate":"2024-11-01T20:22:32Z"},"150":{"iteration":150,"metrics":{"loss":16.525577545166016},"createdDate":"2024-11-01T20:24:26Z"},"380":{"iteration":380,"metrics":{"loss":16.15766716003418},"createdDate":"2024-11-01T20:27:33Z"},"160":{"createdDate":"2024-11-01T20:24:34Z","metrics":{"loss":16.307645797729492},"iteration":160},"510":{"createdDate":"2024-11-01T20:29:23Z","metrics":{"loss":16.168960571289062},"iteration":510},"430":{"createdDate":"2024-11-01T20:28:16Z","metrics":{"loss":16.25580406188965},"iteration":430},"550":{"metrics":{"loss":16.12266731262207},"iteration":550,"createdDate":"2024-11-01T20:29:57Z"},"440":{"iteration":440,"metrics":{"loss":16.279769897460938},"createdDate":"2024-11-01T20:28:24Z"}},"progress":[{"currentRowIndex":0,"tableIndex":0,"tableDone":false,"odColumnHeader":{"iterationCount":1,"elapsedTime":2.113047,"loss":35.192291259765625},"isLast":false,"percentComplete":0,"count":1},{"isLast":false,"currentRowIndex":0,"tableIndex":0,"count":2,"odColumnHeader":{"iterationCount":2,"elapsedTime":2.794183,"loss":35.08110809326172},"tableDone":false,"percentComplete":0},{"tableIndex":0,"currentRowIndex":0,"odColumnHeader":{"elapsedTime":3.517043,"iterationCount":3,"loss":34.965885162353516},"tableDone":false,"percentComplete":0,"count":3,"isLast":false},{"currentRowIndex":0,"count":4,"tableDone":false,"isLast":false,"percentComplete":0,"odColumnHeader":{"elapsedTime":4.200208,"iterationCount":4,"loss":34.7535514831543},"tableIndex":0},{"isLast":false,"tableDone":false,"tableIndex":0,"odColumnHeader":{"iterationCount":5,"loss":34.795753479003906,"elapsedTime":4.200287},"percentComplete":0,"count":5,"currentRowIndex":0},{"count":10,"odColumnHeader":{"loss":33.10317611694336,"elapsedTime":0,"iterationCount":10},"currentRowIndex":0,"isLast":false,"tableDone":false,"tableIndex":0,"percentComplete":0},{"percentComplete":0,"odColumnHeader":{"iterationCount":20,"elapsedTime":0,"loss":25.561264038085938},"count":20,"tableDone":false,"currentRowIndex":0,"isLast":false,"tableIndex":0},{"tableIndex":0,"tableDone":false,"percentComplete":0,"odColumnHeader":{"iterationCount":30,"elapsedTime":0,"loss":21.163982391357422},"isLast":false,"currentRowIndex":0,"count":30},{"count":40,"tableDone":false,"odColumnHeader":{"loss":18.90729522705078,"elapsedTime":0,"iterationCount":40},"percentComplete":0,"isLast":false,"currentRowIndex":0,"tableIndex":0},{"isLast":false,"count":50,"tableIndex":0,"currentRowIndex":0,"percentComplete":0,"odColumnHeader":{"loss":17.460372924804688,"elapsedTime":0,"iterationCount":50},"tableDone":false},{"tableDone":false,"count":60,"percentComplete":0,"isLast":false,"odColumnHeader":{"iterationCount":60,"loss":17.07047462463379,"elapsedTime":0},"currentRowIndex":0,"tableIndex":0},{"count":70,"isLast":false,"tableIndex":0,"odColumnHeader":{"loss":16.85935401916504,"iterationCount":70,"elapsedTime":0},"percentComplete":0,"tableDone":false,"currentRowIndex":0},{"isLast":false,"odColumnHeader":{"elapsedTime":0,"loss":16.961244583129883,"iterationCount":80},"count":80,"tableDone":false,"currentRowIndex":0,"percentComplete":0,"tableIndex":0},{"tableIndex":0,"percentComplete":0,"tableDone":false,"odColumnHeader":{"elapsedTime":0,"loss":16.609691619873047,"iterationCount":90},"currentRowIndex":0,"isLast":false,"count":90},{"odColumnHeader":{"loss":16.61199188232422,"elapsedTime":0,"iterationCount":100},"count":100,"tableDone":false,"currentRowIndex":0,"isLast":false,"tableIndex":0,"percentComplete":0},{"tableIndex":0,"isLast":false,"tableDone":false,"percentComplete":0,"currentRowIndex":0,"count":110,"odColumnHeader":{"iterationCount":110,"elapsedTime":0,"loss":16.5277156829834}},{"percentComplete":0,"isLast":false,"tableIndex":0,"count":120,"tableDone":false,"odColumnHeader":{"iterationCount":120,"elapsedTime":0,"loss":16.658288955688477},"currentRowIndex":0},{"percentComplete":0,"odColumnHeader":{"elapsedTime":0,"iterationCount":130,"loss":16.38890266418457},"isLast":false,"currentRowIndex":0,"tableDone":false,"count":130,"tableIndex":0},{"currentRowIndex":0,"tableIndex":0,"count":140,"percentComplete":0,"tableDone":false,"odColumnHeader":{"loss":16.625226974487305,"iterationCount":140,"elapsedTime":0},"isLast":false},{"odColumnHeader":{"elapsedTime":0,"iterationCount":150,"loss":16.525577545166016},"tableIndex":0,"currentRowIndex":0,"percentComplete":0,"tableDone":false,"count":150,"isLast":false},{"count":160,"currentRowIndex":0,"tableIndex":0,"percentComplete":0,"tableDone":false,"odColumnHeader":{"iterationCount":160,"loss":16.307645797729492,"elapsedTime":0},"isLast":false},{"percentComplete":0,"tableIndex":0,"isLast":false,"count":170,"currentRowIndex":0,"tableDone":false,"odColumnHeader":{"iterationCount":170,"loss":16.413734436035156,"elapsedTime":0}},{"count":180,"currentRowIndex":0,"percentComplete":0,"odColumnHeader":{"loss":16.58378028869629,"elapsedTime":0,"iterationCount":180},"tableDone":false,"tableIndex":0,"isLast":false},{"tableDone":false,"tableIndex":0,"count":190,"percentComplete":0,"currentRowIndex":0,"isLast":false,"odColumnHeader":{"elapsedTime":0,"iterationCount":190,"loss":16.373844146728516}},{"percentComplete":0,"tableDone":false,"currentRowIndex":0,"tableIndex":0,"isLast":false,"odColumnHeader":{"loss":16.406694412231445,"iterationCount":200,"elapsedTime":0},"count":200},{"isLast":false,"odColumnHeader":{"elapsedTime":0,"loss":16.56757926940918,"iterationCount":210},"count":210,"percentComplete":0,"currentRowIndex":0,"tableIndex":0,"tableDone":false},{"tableIndex":0,"count":220,"odColumnHeader":{"iterationCount":220,"loss":16.627521514892578,"elapsedTime":0},"tableDone":false,"isLast":false,"currentRowIndex":0,"percentComplete":0},{"count":230,"isLast":false,"odColumnHeader":{"elapsedTime":0,"iterationCount":230,"loss":16.599275588989258},"tableIndex":0,"percentComplete":0,"tableDone":false,"currentRowIndex":0},{"count":240,"isLast":false,"currentRowIndex":0,"percentComplete":0,"tableDone":false,"odColumnHeader":{"iterationCount":240,"loss":16.412261962890625,"elapsedTime":0},"tableIndex":0},{"isLast":false,"percentComplete":0,"tableDone":false,"currentRowIndex":0,"odColumnHeader":{"iterationCount":250,"loss":16.558862686157227,"elapsedTime":0},"tableIndex":0,"count":250},{"odColumnHeader":{"loss":16.36216926574707,"elapsedTime":0,"iterationCount":260},"count":260,"percentComplete":0,"isLast":false,"tableDone":false,"tableIndex":0,"currentRowIndex":0},{"tableIndex":0,"count":270,"tableDone":false,"currentRowIndex":0,"isLast":false,"percentComplete":0,"odColumnHeader":{"iterationCount":270,"loss":16.621126174926758,"elapsedTime":0}},{"tableDone":false,"odColumnHeader":{"elapsedTime":0,"iterationCount":280,"loss":16.573589324951172},"currentRowIndex":0,"tableIndex":0,"isLast":false,"percentComplete":0,"count":280},{"count":290,"percentComplete":0,"odColumnHeader":{"elapsedTime":0,"loss":16.720428466796875,"iterationCount":290},"isLast":false,"tableDone":false,"tableIndex":0,"currentRowIndex":0},{"percentComplete":0,"count":300,"isLast":false,"tableDone":false,"tableIndex":0,"odColumnHeader":{"iterationCount":300,"elapsedTime":0,"loss":16.87462615966797},"currentRowIndex":0},{"tableIndex":0,"count":310,"isLast":false,"odColumnHeader":{"iterationCount":310,"loss":16.622474670410156,"elapsedTime":0},"percentComplete":0,"tableDone":false,"currentRowIndex":0},{"tableIndex":0,"tableDone":false,"percentComplete":0,"currentRowIndex":0,"count":320,"odColumnHeader":{"iterationCount":320,"loss":16.467905044555664,"elapsedTime":0},"isLast":false},{"tableDone":false,"currentRowIndex":0,"percentComplete":0,"odColumnHeader":{"iterationCount":330,"loss":16.493227005004883,"elapsedTime":0},"isLast":false,"tableIndex":0,"count":330},{"currentRowIndex":0,"count":340,"tableDone":false,"isLast":false,"odColumnHeader":{"elapsedTime":0,"iterationCount":340,"loss":16.258331298828125},"tableIndex":0,"percentComplete":0},{"tableIndex":0,"percentComplete":0,"odColumnHeader":{"elapsedTime":0,"loss":16.155139923095703,"iterationCount":350},"isLast":false,"currentRowIndex":0,"tableDone":false,"count":350},{"tableDone":false,"isLast":false,"tableIndex":0,"odColumnHeader":{"loss":16.25139617919922,"iterationCount":360,"elapsedTime":0},"percentComplete":0,"currentRowIndex":0,"count":360},{"percentComplete":0,"tableIndex":0,"odColumnHeader":{"iterationCount":370,"loss":16.384326934814453,"elapsedTime":0},"count":370,"currentRowIndex":0,"isLast":false,"tableDone":false},{"tableDone":false,"count":380,"tableIndex":0,"odColumnHeader":{"loss":16.15766716003418,"elapsedTime":0,"iterationCount":380},"currentRowIndex":0,"isLast":false,"percentComplete":0},{"isLast":false,"percentComplete":0,"currentRowIndex":0,"count":390,"tableIndex":0,"tableDone":false,"odColumnHeader":{"iterationCount":390,"elapsedTime":0,"loss":16.27922248840332}},{"isLast":false,"percentComplete":0,"tableIndex":0,"odColumnHeader":{"iterationCount":400,"loss":16.297212600708008,"elapsedTime":0},"count":400,"tableDone":false,"currentRowIndex":0},{"isLast":false,"percentComplete":0,"count":410,"currentRowIndex":0,"tableDone":false,"tableIndex":0,"odColumnHeader":{"loss":16.34536361694336,"iterationCount":410,"elapsedTime":0}},{"count":420,"tableDone":false,"percentComplete":0,"isLast":false,"odColumnHeader":{"iterationCount":420,"loss":16.47896957397461,"elapsedTime":0},"currentRowIndex":0,"tableIndex":0},{"count":430,"isLast":false,"tableDone":false,"tableIndex":0,"percentComplete":0,"odColumnHeader":{"loss":16.25580406188965,"elapsedTime":0,"iterationCount":430},"currentRowIndex":0},{"odColumnHeader":{"iterationCount":440,"loss":16.279769897460938,"elapsedTime":0},"currentRowIndex":0,"count":440,"tableIndex":0,"isLast":false,"percentComplete":0,"tableDone":false},{"isLast":false,"currentRowIndex":0,"percentComplete":0,"odColumnHeader":{"loss":16.570432662963867,"iterationCount":450,"elapsedTime":0},"tableDone":false,"tableIndex":0,"count":450},{"percentComplete":0,"currentRowIndex":0,"tableDone":false,"odColumnHeader":{"elapsedTime":0,"iterationCount":460,"loss":16.33327865600586},"tableIndex":0,"count":460,"isLast":false},{"currentRowIndex":0,"tableIndex":0,"count":470,"tableDone":false,"odColumnHeader":{"loss":16.223344802856445,"elapsedTime":0,"iterationCount":470},"isLast":false,"percentComplete":0},{"tableDone":false,"odColumnHeader":{"elapsedTime":0,"loss":16.18989372253418,"iterationCount":480},"isLast":false,"currentRowIndex":0,"count":480,"tableIndex":0,"percentComplete":0},{"tableDone":false,"tableIndex":0,"count":490,"percentComplete":0,"currentRowIndex":0,"isLast":false,"odColumnHeader":{"iterationCount":490,"loss":16.282581329345703,"elapsedTime":0}},{"percentComplete":0,"currentRowIndex":0,"isLast":false,"count":500,"tableDone":false,"odColumnHeader":{"elapsedTime":0,"loss":16.452993392944336,"iterationCount":500},"tableIndex":0},{"tableIndex":0,"odColumnHeader":{"loss":16.168960571289062,"elapsedTime":0,"iterationCount":510},"tableDone":false,"isLast":false,"percentComplete":0,"currentRowIndex":0,"count":510},{"tableIndex":0,"isLast":false,"tableDone":false,"currentRowIndex":0,"percentComplete":0,"count":520,"odColumnHeader":{"elapsedTime":0,"iterationCount":520,"loss":16.070953369140625}},{"odColumnHeader":{"iterationCount":530,"loss":16.089946746826172,"elapsedTime":0},"tableIndex":0,"currentRowIndex":0,"tableDone":false,"percentComplete":0,"count":530,"isLast":false},{"tableIndex":0,"isLast":false,"currentRowIndex":0,"tableDone":false,"percentComplete":0,"odColumnHeader":{"loss":15.98532485961914,"elapsedTime":0,"iterationCount":540},"count":540},{"currentRowIndex":0,"count":550,"isLast":false,"tableIndex":0,"percentComplete":0,"odColumnHeader":{"iterationCount":550,"loss":16.12266731262207,"elapsedTime":0},"tableDone":false},{"tableDone":false,"currentRowIndex":0,"percentComplete":0,"tableIndex":0,"count":560,"isLast":false,"odColumnHeader":{"iterationCount":560,"elapsedTime":0,"loss":16.156625747680664}},{"isLast":false,"percentComplete":0,"tableDone":false,"count":570,"tableIndex":0,"currentRowIndex":0,"odColumnHeader":{"loss":16.239961624145508,"elapsedTime":0,"iterationCount":570}},{"currentRowIndex":0,"count":580,"isLast":false,"tableIndex":0,"odColumnHeader":{"iterationCount":580,"elapsedTime":0,"loss":15.86856746673584},"percentComplete":0,"tableDone":false},{"count":590,"tableDone":false,"currentRowIndex":0,"isLast":false,"tableIndex":0,"percentComplete":0,"odColumnHeader":{"iterationCount":590,"elapsedTime":0,"loss":15.981330871582031}},{"currentRowIndex":0,"percentComplete":0,"tableIndex":0,"odColumnHeader":{"loss":15.928003311157227,"iterationCount":600,"elapsedTime":0},"tableDone":false,"count":600,"isLast":false},{"isLast":false,"count":610,"percentComplete":0,"tableDone":false,"odColumnHeader":{"elapsedTime":0,"iterationCount":610,"loss":15.930257797241211},"tableIndex":0,"currentRowIndex":0}],"featureExtractionCheckpointMayBeAvailable":false,"analysedDataType":"datasource","snapshottableCheckpoints":{"610":{"modelURL":"file:\/\/\/Users\/teerthrajparmar\/Library\/Caches\/com.apple.dt.createml\/projects\/EB82AE05-2BC3-4BCF-94A7-5AD7AFF1B32233968d2ea6edb189a466bbfab88d829d1c8088a7\/sessions\/checkpoint.sessions\/760DAA1F-53F5-4198-B2A9-D6A73D4D10C7\/training-000000610.checkpoint.model\/checkpointModel.mlmodel","iteration":610,"createdDate":"2024-11-01T20:30:47Z"}}},"evaluationContainerEntity":{"createdDate":"2024-11-01T20:41:29Z","evaluationEntities":[{"accuracy":0.011111111111111112,"finishTime":"2024-11-01T20:41:29Z","startTime":"2024-11-01T20:41:28Z","dataSourceID":"F3942739-C296-4D38-8CE9-EEE291DB399A","dataResult":{"dataURL":"file:\/\/\/Users\/teerthrajparmar\/development\/BoardSolverData\/finalRotatedImages\/test\/","dataAnalysis":{"issues":[{"description":"27 classes found, including A, I, R","severity":"debug"},{"severity":"warning","description":"Less than 50 total images found - add more to improve model validation"},{"severity":"debug","description":"Smallest class is \"C\" with 1 images"},{"description":"Largest class is \"A\" with 24 images","severity":"debug"}],"objectDetectorAnalysis":{"labelStats":{"L":12,"A":24,"U":12,"Z":4,"Q":4,"I":24,"H":8,"X":4,"P":6,"N":14,"V":4,"D":8,"K":2,"J":3,"O":12,"B":3,"F":4,"R":19,"Board":5,"W":2,"C":1,"Y":4,"S":8,"G":8,"T":8,"E":18,"M":7},"details":{}},"summary":{"classCount":27,"suggestedMaxIterations":5000,"canUseValidation":1,"sampleCount":4,"counterExamples":0},"classifierAnalysis":{}},"classesCount":27,"dataSourceID":"F3942739-C296-4D38-8CE9-EEE291DB399A","createdDate":"2024-11-01T20:41:27Z","itemsCount":4},"analysedDataType":"datasource","evaluationResult":{"objectDetector":{"meanAveragePrecision":{"variedIoU":0.00537037037037037,"IoU50":0.011111111111111112},"confusionMetrics":{"isValid":true,"meanAveragePrecision":{"variedIoU":0.00537037037037037,"IoU50":0.011111111111111112},"averagePrecision":{"variedIoU":{"E":0,"W":0,"K":0,"M":0,"D":0,"X":0,"L":0,"O":0.02,"Q":0,"U":0,"T":0,"B":0,"Y":0,"F":0,"R":0,"J":0,"H":0,"V":0,"G":0,"Z":0,"P":0,"Board":0.125,"I":0,"N":0,"C":0,"S":0,"A":0},"IoU50":{"R":0,"E":0,"B":0,"I":0,"F":0,"Z":0,"T":0,"U":0,"J":0,"V":0,"W":0,"H":0,"L":0,"X":0,"D":0,"Q":0,"S":0,"O":0.05,"M":0,"A":0,"C":0,"K":0,"N":0,"P":0,"G":0,"Y":0,"Board":0.25}}},"averagePrecision":{"Z":{"variedIoU":0,"IoU50":0},"B":{"IoU50":0,"variedIoU":0},"D":{"variedIoU":0,"IoU50":0},"U":{"IoU50":0,"variedIoU":0},"P":{"IoU50":0,"variedIoU":0},"K":{"IoU50":0,"variedIoU":0},"E":{"variedIoU":0,"IoU50":0},"L":{"IoU50":0,"variedIoU":0},"A":{"variedIoU":0,"IoU50":0},"H":{"variedIoU":0,"IoU50":0},"F":{"IoU50":0,"variedIoU":0},"G":{"variedIoU":0,"IoU50":0},"T":{"variedIoU":0,"IoU50":0},"W":{"IoU50":0,"variedIoU":0},"Y":{"IoU50":0,"variedIoU":0},"Q":{"IoU50":0,"variedIoU":0},"J":{"IoU50":0,"variedIoU":0},"C":{"variedIoU":0,"IoU50":0},"O":{"variedIoU":0.02,"IoU50":0.05},"M":{"IoU50":0,"variedIoU":0},"X":{"variedIoU":0,"IoU50":0},"I":{"variedIoU":0,"IoU50":0},"S":{"IoU50":0,"variedIoU":0},"N":{"variedIoU":0,"IoU50":0},"Board":{"IoU50":0.25,"variedIoU":0.125},"V":{"variedIoU":0,"IoU50":0},"R":{"variedIoU":0,"IoU50":0}},"rawDetails":[{"annotations":[{"label":"Board","coordinates":{"height":0.8237020203124998,"x":0.4659593749999999,"y":0.49817440078124997,"width":0.4306043687500002}},{"label":"Q","coordinates":{"y":0.86875,"x":0.3007812499999999,"height":0.04921875,"width":0.02578125}},{"label":"E","coordinates":{"height":0.05078125,"x":0.2734374999999999,"y":0.86953125,"width":0.025}},{"coordinates":{"width":0.02734375,"y":0.81640625,"height":0.05078125,"x":0.3007812499999999},"label":"T"},{"coordinates":{"y":0.81640625,"height":0.053125,"width":0.0265625,"x":0.27265624999999993},"label":"G"},{"label":"H","coordinates":{"height":0.05234375,"x":0.3273437499999999,"width":0.02734375,"y":0.7640625}},{"coordinates":{"width":0.0265625,"y":0.7640625,"x":0.3007812499999999,"height":0.0484375},"label":"F"},{"label":"G","coordinates":{"y":0.71328125,"height":0.04765625,"width":0.028125,"x":0.3007812499999999}},{"coordinates":{"width":0.02734375,"y":0.59921875,"x":0.29921875,"height":0.05234375},"label":"I"},{"label":"X","coordinates":{"height":0.046875,"x":0.35390625,"width":0.028125,"y":0.546875}},{"coordinates":{"y":0.54765625,"width":0.025,"x":0.32812499999999994,"height":0.0515625},"label":"O"},{"label":"Board","coordinates":{"height":0.0515625,"width":0.02421875,"y":0.54765625,"x":0.30078124999999994}},{"label":"I","coordinates":{"y":0.4953125,"x":0.32968749999999997,"width":0.0265625,"height":0.046875}},{"coordinates":{"x":0.30156249999999996,"width":0.025,"y":0.49765625,"height":0.053125},"label":"P"},{"coordinates":{"y":0.3953125,"x":0.32734374999999993,"width":0.02421875,"height":0.04765625},"label":"S"},{"label":"N","coordinates":{"x":0.32499999999999996,"y":0.3453125,"width":0.0234375,"height":0.04765625}},{"label":"R","coordinates":{"height":0.05078125,"x":0.30078124999999994,"width":0.0265625,"y":0.39609375}},{"label":"A","coordinates":{"height":0.04765625,"width":0.025,"y":0.34375,"x":0.29843749999999997}},{"label":"N","coordinates":{"x":0.27109374999999997,"y":0.34296875,"width":0.02734375,"height":0.04921875}},{"coordinates":{"width":0.025,"y":0.32890625,"height":0.05078125,"x":0.46406249999999993},"label":"A"},{"coordinates":{"y":0.3296875,"height":0.0515625,"x":0.43671874999999993,"width":0.02734375},"label":"U"},{"label":"R","coordinates":{"y":0.2765625,"x":0.4625,"height":0.053125,"width":0.02578125000000009}},{"label":"L","coordinates":{"x":0.43671875,"width":0.02656250000000009,"y":0.278125,"height":0.046875}},{"coordinates":{"y":0.2296875,"width":0.02734375,"height":0.04921875,"x":0.48828125},"label":"E"},{"coordinates":{"x":0.4625,"width":0.0234375,"height":0.05234375,"y":0.22421875},"label":"I"},{"coordinates":{"y":0.22734375,"x":0.43671875,"width":0.025,"height":0.05078125},"label":"U"},{"label":"Y","coordinates":{"y":0.1734375,"width":0.02578125,"x":0.46328125,"height":0.05234375}},{"label":"I","coordinates":{"height":0.05234375,"x":0.4890625,"y":0.1296875,"width":0.025}},{"label":"Z","coordinates":{"y":0.121875,"width":0.0234375,"x":0.46328125,"height":0.05}},{"label":"A","coordinates":{"x":0.54765625,"width":0.02578125,"height":0.04921875,"y":0.859375}},{"label":"N","coordinates":{"height":0.04921875,"width":0.0234375,"x":0.5218749999999999,"y":0.8609375}},{"label":"H","coordinates":{"width":0.0265625,"height":0.05625,"x":0.49531249999999993,"y":0.86171875}},{"coordinates":{"x":0.54765625,"y":0.80703125,"width":0.02578125,"height":0.05},"label":"A"},{"label":"T","coordinates":{"y":0.8078125,"width":0.02265625,"height":0.0484375,"x":0.5234374999999999}},{"label":"L","coordinates":{"y":0.75546875,"x":0.54765625,"width":0.0234375,"height":0.05234375}},{"label":"R","coordinates":{"height":0.04921875,"x":0.5468749999999999,"width":0.01953125,"y":0.70703125}},{"label":"U","coordinates":{"width":0.0234375,"x":0.5742187499999999,"height":0.0515625,"y":0.49453125}},{"coordinates":{"y":0.4953125,"x":0.5460937499999999,"width":0.025,"height":0.05},"label":"D"},{"label":"E","coordinates":{"y":0.4953125,"x":0.5187499999999999,"height":0.04765625,"width":0.02578125}},{"coordinates":{"width":0.0234375,"y":0.4953125,"x":0.4921874999999999,"height":0.05},"label":"S"},{"coordinates":{"x":0.65234375,"width":0.024218750000000087,"height":0.05078125,"y":0.2796875},"label":"I"},{"label":"A","coordinates":{"x":0.6265625,"height":0.0515625,"width":0.02734375000000009,"y":0.27890625}},{"label":"R","coordinates":{"width":0.0265625,"x":0.6265625,"y":0.228125,"height":0.046875}},{"label":"M","coordinates":{"width":0.02421875,"x":0.6,"height":0.05234375,"y":0.234375}},{"label":"R","coordinates":{"y":0.1765625,"height":0.046875,"x":0.653125,"width":0.025}},{"label":"L","coordinates":{"y":0.1796875,"x":0.62734375,"width":0.025,"height":0.0515625}},{"label":"D","coordinates":{"x":0.65390625,"height":0.05,"width":0.02421875,"y":0.12578125}},{"label":"E","coordinates":{"height":0.05078125,"width":0.028125,"y":0.12421875,"x":0.62734375}},{"label":"M","coordinates":{"width":0.02421875,"y":0.12421875,"height":0.05234375,"x":0.60234375}}],"inferences":[],"imagePath":"\/Users\/teerthrajparmar\/development\/BoardSolverData\/finalRotatedImages\/test\/rotated_IMG_7829_jpg.rf.a83da2ff63dffc58ced8be215df6db48.jpg"},{"imagePath":"\/Users\/teerthrajparmar\/development\/BoardSolverData\/finalRotatedImages\/test\/rotated_IMG_7825_jpg.rf.ccf1621b17f80109304c5e40a7fc7afb.jpg","annotations":[{"coordinates":{"y":0.46875,"width":0.4593750000000001,"x":0.44140625,"height":0.88046875},"label":"Board"},{"label":"G","coordinates":{"width":0.02578125,"y":0.7546875,"height":0.05625,"x":0.24218749999999992}},{"coordinates":{"x":0.2679687499999999,"y":0.75625,"width":0.02734375,"height":0.0546875},"label":"B"},{"coordinates":{"x":0.2695312499999999,"height":0.0546875,"width":0.02578125,"y":0.81015625},"label":"I"},{"label":"E","coordinates":{"width":0.028125,"height":0.0578125,"x":0.29921874999999987,"y":0.859375}},{"label":"Q","coordinates":{"x":0.29765624999999984,"height":0.05546875,"y":0.80546875,"width":0.0265625}},{"label":"T","coordinates":{"y":0.753125,"height":0.05859375,"width":0.02890625,"x":0.2960937499999999}},{"label":"O","coordinates":{"width":0.02734375,"height":0.05390625,"x":0.29374999999999984,"y":0.69765625}},{"label":"X","coordinates":{"x":0.3242187499999999,"y":0.7515625,"width":0.028125,"height":0.05625}},{"coordinates":{"y":0.746875,"width":0.028125,"height":0.05390625,"x":0.4179687499999999},"label":"F"},{"label":"G","coordinates":{"y":0.69375,"x":0.4164062499999999,"width":0.0265625,"height":0.053125}},{"coordinates":{"width":0.025,"x":0.4453124999999999,"y":0.7484375,"height":0.0546875},"label":"A"},{"label":"H","coordinates":{"width":0.028125,"height":0.05625,"y":0.69375,"x":0.44453124999999993}},{"label":"L","coordinates":{"y":0.69609375,"x":0.47187499999999993,"width":0.0265625,"height":0.05546875}},{"coordinates":{"x":0.53203125,"width":0.028125,"y":0.57890625,"height":0.05625},"label":"R"},{"coordinates":{"width":0.02734375,"y":0.52578125,"height":0.05390625,"x":0.5304687499999999},"label":"E"},{"coordinates":{"width":0.0296875,"x":0.5328124999999999,"height":0.05390625,"y":0.4734375},"label":"I"},{"coordinates":{"width":0.0265625,"x":0.5578124999999999,"y":0.58125,"height":0.05234375},"label":"A"},{"label":"U","coordinates":{"width":0.0265625,"height":0.05390625,"x":0.5585937499999999,"y":0.52734375}},{"coordinates":{"height":0.05390625,"x":0.5882812499999999,"width":0.02890625,"y":0.58203125},"label":"R"},{"coordinates":{"y":0.58203125,"height":0.05390625,"width":0.0265625,"x":0.6164062499999999},"label":"T"},{"coordinates":{"y":0.24375,"width":0.02890625,"x":0.61796875,"height":0.0546875},"label":"A"},{"label":"I","coordinates":{"x":0.64609375,"y":0.2421875,"width":0.02734375,"height":0.05625}},{"coordinates":{"y":0.18828125,"width":0.02890625,"height":0.05703125,"x":0.61953125},"label":"R"},{"label":"M","coordinates":{"y":0.190625,"width":0.028125,"x":0.590625,"height":0.0609375}},{"coordinates":{"x":0.59296875,"width":0.02890625,"y":0.07265625,"height":0.05625},"label":"M"},{"coordinates":{"x":0.61875,"width":0.028125,"height":0.05859375,"y":0.13046875},"label":"L"},{"coordinates":{"x":0.64765625,"height":0.05546875,"width":0.028125,"y":0.1296875},"label":"R"},{"coordinates":{"y":0.0734375,"height":0.0546875,"width":0.02890625,"x":0.62109375},"label":"E"},{"coordinates":{"width":0.028125,"height":0.05546875,"y":0.075,"x":0.6484375},"label":"D"},{"label":"E","coordinates":{"y":0.41484375,"width":0.025,"x":0.47187499999999993,"height":0.053125}},{"coordinates":{"y":0.3625,"width":0.0265625,"height":0.05390625,"x":0.47187499999999993},"label":"A"},{"label":"A","coordinates":{"x":0.4453124999999999,"width":0.0265625,"y":0.41796875,"height":0.05546875}},{"label":"Z","coordinates":{"x":0.4437499999999999,"width":0.02734375,"y":0.3640625,"height":0.05390625}},{"label":"L","coordinates":{"x":0.4156249999999999,"height":0.053125,"width":0.028125,"y":0.3625}},{"coordinates":{"y":0.359375,"width":0.027343749999999955,"height":0.05546875,"x":0.38749999999999984},"label":"U"},{"label":"N","coordinates":{"width":0.02734375,"y":0.421875,"height":0.05390625,"x":0.24062499999999995}},{"label":"N","coordinates":{"width":0.02734375,"x":0.26796875,"height":0.053125,"y":0.421875}},{"label":"S","coordinates":{"x":0.29609374999999993,"height":0.053125,"y":0.42109375,"width":0.028125}},{"coordinates":{"height":0.05390625,"y":0.475,"width":0.02734375,"x":0.27031249999999996},"label":"A"},{"label":"I","coordinates":{"y":0.47578125,"height":0.05546875,"width":0.02890625,"x":0.29765624999999996}},{"label":"P","coordinates":{"width":0.028125,"y":0.584375,"height":0.053125,"x":0.27031249999999996}},{"label":"R","coordinates":{"width":0.02734375,"x":0.26953124999999994,"height":0.05390625,"y":0.52890625}},{"label":"H","coordinates":{"width":0.0265625,"y":0.5828125,"x":0.29921875,"height":0.05546875}},{"label":"N","coordinates":{"x":0.29765624999999996,"height":0.053125,"y":0.52890625,"width":0.02734375}},{"label":"U","coordinates":{"height":0.05234375,"width":0.02734375,"y":0.52578125,"x":0.32499999999999996}},{"coordinates":{"width":0.028125,"x":0.3265625,"y":0.5796875,"height":0.05546875},"label":"S"},{"coordinates":{"width":0.02734375,"height":0.0546875,"x":0.35390625,"y":0.5265625},"label":"D"},{"label":"I","coordinates":{"width":0.028125,"x":0.35390625,"y":0.4734375,"height":0.053125}}],"inferences":[]},{"annotations":[{"label":"Board","coordinates":{"x":0.5015625,"height":0.85,"y":0.490625,"width":0.4445312500000001}},{"label":"Y","coordinates":{"width":0.02734375,"x":0.30234374999999986,"y":0.86875,"height":0.05625}},{"coordinates":{"y":0.8140625,"width":0.0265625,"x":0.3039062499999999,"height":0.0546875},"label":"Z"},{"coordinates":{"x":0.3312499999999999,"y":0.86875,"width":0.0265625,"height":0.05390625},"label":"I"},{"coordinates":{"y":0.8140625,"width":0.028125,"height":0.05390625,"x":0.3320312499999999},"label":"I"},{"coordinates":{"y":0.759375,"height":0.05859375,"x":0.3351562499999999,"width":0.028125},"label":"H"},{"label":"V","coordinates":{"y":0.75859375,"x":0.36171874999999987,"height":0.05390625,"width":0.02734375}},{"coordinates":{"y":0.8109375,"width":0.028125,"x":0.44843749999999993,"height":0.0546875},"label":"W"},{"label":"X","coordinates":{"x":0.4507812499999999,"y":0.75625,"width":0.02734375,"height":0.05390625}},{"label":"I","coordinates":{"y":0.753125,"width":0.0265625,"height":0.05546875,"x":0.4804687499999999}},{"coordinates":{"x":0.47968749999999993,"width":0.02578125,"y":0.7,"height":0.0546875},"label":"A"},{"label":"G","coordinates":{"y":0.753125,"width":0.025,"x":0.5070312499999999,"height":0.05546875}},{"coordinates":{"width":0.02578125,"height":0.05390625,"x":0.5070312499999999,"y":0.69921875},"label":"A"},{"coordinates":{"height":0.05234375,"x":0.5054687499999999,"width":0.025,"y":0.64453125},"label":"A"},{"coordinates":{"height":0.053125,"width":0.025,"x":0.5328124999999999,"y":0.75546875},"label":"S"},{"coordinates":{"x":0.7023437499999999,"y":0.8703125,"width":0.028125,"height":0.05390625},"label":"E"},{"label":"J","coordinates":{"y":0.81640625,"width":0.02578125,"x":0.6749999999999999,"height":0.05625}},{"label":"J","coordinates":{"x":0.64921875,"y":0.81640625,"width":0.02734375,"height":0.05546875}},{"label":"H","coordinates":{"x":0.6453125,"y":0.70078125,"width":0.0265625,"height":0.0546875}},{"label":"I","coordinates":{"x":0.67265625,"height":0.05234375,"y":0.7,"width":0.02421875}},{"coordinates":{"y":0.64609375,"width":0.0265625,"height":0.05234375,"x":0.6195312499999999},"label":"I"},{"coordinates":{"x":0.6460937499999999,"y":0.6484375,"width":0.02578125,"height":0.0515625},"label":"O"},{"label":"A","coordinates":{"y":0.64921875,"width":0.025,"x":0.6718749999999999,"height":0.05234375}},{"coordinates":{"y":0.596875,"x":0.6453125,"height":0.0515625,"width":0.02421875},"label":"N"},{"label":"K","coordinates":{"x":0.69765625,"height":0.05078125,"y":0.23046875,"width":0.02578125}},{"coordinates":{"width":0.0234375,"y":0.17890625,"x":0.69765625,"height":0.05234375},"label":"P"},{"coordinates":{"height":0.05078125,"x":0.7,"width":0.025,"y":0.12734375},"label":"V"},{"label":"A","coordinates":{"width":0.0234375,"height":0.05078125,"x":0.675,"y":0.125}},{"label":"O","coordinates":{"height":0.05078125,"width":0.02421875,"x":0.6164062499999999,"y":0.48671875}},{"coordinates":{"x":0.590625,"height":0.05078125,"width":0.025,"y":0.48671875},"label":"F"},{"label":"N","coordinates":{"width":0.02734375,"y":0.4859375,"x":0.5648437499999999,"height":0.053125}},{"coordinates":{"y":0.43671875,"x":0.5640624999999999,"width":0.02578125,"height":0.05078125},"label":"G"},{"coordinates":{"height":0.05234375,"y":0.4359375,"x":0.5898437499999999,"width":0.0234375},"label":"D"},{"coordinates":{"height":0.053125,"y":0.38515625,"width":0.02734375,"x":0.58671875},"label":"O"},{"coordinates":{"width":0.02578125000000009,"y":0.27890625,"height":0.0515625,"x":0.61640625},"label":"U"},{"coordinates":{"width":0.02421875,"y":0.2296875,"height":0.05,"x":0.6171875},"label":"U"},{"label":"I","coordinates":{"x":0.59140625,"width":0.02578125,"height":0.05078125,"y":0.178125}},{"label":"R","coordinates":{"x":0.6171875,"height":0.053125,"y":0.17734375,"width":0.0265625}},{"label":"L","coordinates":{"x":0.61640625,"y":0.12578125,"width":0.02734375,"height":0.05078125}},{"coordinates":{"y":0.1265625,"x":0.58984375,"height":0.0515625,"width":0.02578125},"label":"E"},{"label":"E","coordinates":{"width":0.02578125,"x":0.5359375,"height":0.05234375,"y":0.33125}},{"label":"O","coordinates":{"height":0.05234375,"y":0.2796875,"width":0.025000000000000088,"x":0.53359375}},{"label":"E","coordinates":{"y":0.22734375,"height":0.05234375,"x":0.534375,"width":0.02421875}},{"label":"D","coordinates":{"height":0.05234375,"width":0.025000000000000088,"x":0.5078125,"y":0.278125}},{"label":"M","coordinates":{"x":0.50859375,"y":0.22734375,"width":0.025,"height":0.053125}},{"coordinates":{"width":0.02421875,"y":0.228125,"height":0.05078125,"x":0.4828125},"label":"L"},{"label":"R","coordinates":{"height":0.0515625,"x":0.4789062499999999,"y":0.434375,"width":0.02578125}},{"coordinates":{"height":0.05234375,"width":0.025,"y":0.38359375,"x":0.4781249999999999},"label":"A"},{"label":"A","coordinates":{"x":0.4515624999999999,"y":0.484375,"height":0.05234375,"width":0.025}},{"coordinates":{"y":0.43359375,"width":0.025,"x":0.4515624999999999,"height":0.05390625},"label":"E"},{"coordinates":{"y":0.38125,"x":0.4507812499999999,"width":0.025,"height":0.053125},"label":"L"},{"label":"I","coordinates":{"height":0.05234375,"width":0.02578125,"y":0.3296875,"x":0.4499999999999999}},{"coordinates":{"height":0.05078125,"width":0.025,"x":0.4234374999999999,"y":0.32578125},"label":"N"},{"coordinates":{"y":0.53515625,"width":0.02734375,"height":0.05234375,"x":0.3109375},"label":"Q"},{"label":"O","coordinates":{"y":0.534375,"x":0.33906249999999993,"height":0.05078125,"width":0.0265625}},{"label":"R","coordinates":{"y":0.53515625,"x":0.36953125,"width":0.02890625,"height":0.0515625}},{"coordinates":{"height":0.04921875,"y":0.48203125,"width":0.02890625,"x":0.33828125},"label":"T"},{"coordinates":{"height":0.05078125,"x":0.365625,"y":0.48359375,"width":0.02578125},"label":"T"},{"label":"U","coordinates":{"x":0.36718749999999994,"width":0.02578125,"y":0.27265625,"height":0.05}},{"label":"I","coordinates":{"width":0.0265625,"x":0.36640624999999993,"y":0.21875,"height":0.05078125}},{"label":"S","coordinates":{"y":0.165625,"width":0.025,"x":0.36640624999999993,"height":0.05234375}},{"label":"B","coordinates":{"y":0.21875,"width":0.02578125,"x":0.34062499999999996,"height":0.05078125}},{"label":"P","coordinates":{"x":0.33906249999999993,"height":0.05234375,"y":0.16328125,"width":0.02578125}},{"coordinates":{"y":0.21640625,"height":0.05234375,"x":0.31406249999999997,"width":0.0265625},"label":"N"},{"coordinates":{"height":0.05078125,"x":0.31249999999999994,"width":0.025,"y":0.165625},"label":"R"}],"inferences":[{"classifications":[{"identifier":"Board","confidence":0.98833025},{"identifier":"B","confidence":0.00043286246},{"identifier":"C","confidence":0.00043286246},{"identifier":"D","confidence":0.00043286246},{"confidence":0.00043286246,"identifier":"F"},{"confidence":0.00043286246,"identifier":"G"},{"confidence":0.00043286246,"identifier":"H"},{"identifier":"I","confidence":0.00043286246},{"identifier":"L","confidence":0.00043286246},{"identifier":"M","confidence":0.00043286246},{"identifier":"O","confidence":0.00043286246},{"confidence":0.00043286246,"identifier":"Q"},{"identifier":"R","confidence":0.00043286246},{"identifier":"S","confidence":0.00043286246},{"confidence":0.00043286246,"identifier":"T"},{"identifier":"U","confidence":0.00043286246},{"identifier":"W","confidence":0.00043286246},{"identifier":"X","confidence":0.00043286246},{"confidence":0.00043286246,"identifier":"Y"},{"identifier":"Z","confidence":0.00043286246},{"confidence":0.00043066888,"identifier":"A"},{"identifier":"Blank","confidence":0.00043066888},{"identifier":"E","confidence":0.00043066888},{"identifier":"J","confidence":0.00043066888},{"confidence":0.00043066888,"identifier":"K"},{"identifier":"N","confidence":0.00043066888},{"identifier":"P","confidence":0.00043066888},{"identifier":"V","confidence":0.00043066888}],"coordinates":{"x":0.459716796875,"height":0.7626953125,"width":0.41943359375,"y":0.55078125}},{"classifications":[{"identifier":"M","confidence":0.8700668},{"confidence":0.041011788,"identifier":"T"},{"confidence":0.029186787,"identifier":"R"},{"identifier":"N","confidence":0.026537038},{"confidence":0.0063178716,"identifier":"E"},{"confidence":0.005872951,"identifier":"G"},{"identifier":"A","confidence":0.0042564063},{"identifier":"D","confidence":0.0030996131},{"confidence":0.002919173,"identifier":"F"},{"identifier":"I","confidence":0.0028104146},{"identifier":"W","confidence":0.0028104146},{"identifier":"O","confidence":0.0016264317},{"confidence":0.0012952131,"identifier":"X"},{"identifier":"Z","confidence":0.00053050596},{"confidence":0.00048663185,"identifier":"Q"},{"identifier":"L","confidence":0.00040660793},{"identifier":"H","confidence":0.00026818822},{"confidence":0.00011030322,"identifier":"P"},{"identifier":"S","confidence":8.9911024e-05},{"confidence":6.843743e-05,"identifier":"V"},{"confidence":5.3761232e-05,"identifier":"J"},{"confidence":5.2834315e-05,"identifier":"U"},{"confidence":4.8199723e-05,"identifier":"C"},{"confidence":2.9043424e-05,"identifier":"Blank"},{"confidence":1.8692843e-05,"identifier":"B"},{"identifier":"K","confidence":1.3440308e-05},{"identifier":"Y","confidence":1.0196096e-05},{"identifier":"Board","confidence":2.3172945e-06}],"coordinates":{"width":0.02056884765625,"height":0.055908203125,"y":0.45849609375,"x":0.457763671875}},{"classifications":[{"confidence":0.69403994,"identifier":"I"},{"confidence":0.1410705,"identifier":"Y"},{"identifier":"W","confidence":0.08270942},{"confidence":0.061020672,"identifier":"V"},{"confidence":0.007903844,"identifier":"H"},{"identifier":"J","confidence":0.0026525639},{"identifier":"Z","confidence":0.0016657539},{"confidence":0.0012981876,"identifier":"U"},{"identifier":"T","confidence":0.0009083802},{"identifier":"F","confidence":0.0008650682},{"identifier":"O","confidence":0.0008194151},{"identifier":"M","confidence":0.0008059533},{"confidence":0.00068187044,"identifier":"N"},{"confidence":0.00049252703,"identifier":"R"},{"identifier":"C","confidence":0.00048725933},{"confidence":0.00045653127,"identifier":"B"},{"confidence":0.00039244132,"identifier":"Q"},{"confidence":0.00034239845,"identifier":"G"},{"confidence":0.00032835134,"identifier":"E"},{"confidence":0.00027435774,"identifier":"X"},{"confidence":0.00024231276,"identifier":"K"},{"confidence":0.00017983235,"identifier":"Blank"},{"identifier":"S","confidence":0.00013725203},{"identifier":"A","confidence":0.00011983946},{"confidence":5.3847278e-05,"identifier":"L"},{"confidence":2.5753046e-05,"identifier":"P"},{"identifier":"D","confidence":1.5803005e-05},{"confidence":9.95004e-06,"identifier":"Board"}],"coordinates":{"x":0.32958984375,"height":0.0452880859375,"width":0.0231781005859375,"y":0.861328125}},{"classifications":[{"confidence":0.9889427,"identifier":"A"},{"confidence":0.003340043,"identifier":"N"},{"confidence":0.0014499411,"identifier":"R"},{"identifier":"C","confidence":0.0012462588},{"confidence":0.0011193891,"identifier":"I"},{"confidence":0.00097180577,"identifier":"G"},{"confidence":0.0005471801,"identifier":"K"},{"confidence":0.00038902438,"identifier":"S"},{"identifier":"X","confidence":0.00034349796},{"confidence":0.0003148012,"identifier":"Q"},{"identifier":"H","confidence":0.00028739905},{"confidence":0.00022871095,"identifier":"O"},{"confidence":0.00019548312,"identifier":"J"},{"identifier":"W","confidence":0.00011133476},{"confidence":0.000104861814,"identifier":"F"},{"identifier":"T","confidence":9.32105e-05},{"identifier":"V","confidence":9.2131675e-05},{"identifier":"D","confidence":6.7965986e-05},{"identifier":"P","confidence":4.703678e-05},{"identifier":"L","confidence":4.5094894e-05},{"identifier":"U","confidence":3.08544e-05},{"identifier":"Y","confidence":1.3377433e-05},{"confidence":6.4729516e-06,"identifier":"E"},{"identifier":"Z","confidence":3.8837707e-06},{"identifier":"M","confidence":3.6680058e-06},{"confidence":1.7261203e-06,"identifier":"Blank"},{"confidence":1.2945902e-06,"identifier":"B"},{"identifier":"Board","confidence":8.6306017e-07}],"coordinates":{"height":0.048828125,"y":0.669921875,"width":0.0239715576171875,"x":0.5205078125}},{"classifications":[{"identifier":"O","confidence":0.747399},{"identifier":"F","confidence":0.04774571},{"identifier":"N","confidence":0.04036213},{"identifier":"D","confidence":0.036422785},{"identifier":"E","confidence":0.031622384},{"identifier":"I","confidence":0.027941357},{"identifier":"B","confidence":0.025465813},{"identifier":"R","confidence":0.007658041},{"identifier":"G","confidence":0.00672164},{"identifier":"A","confidence":0.003923199},{"identifier":"M","confidence":0.0037186975},{"identifier":"W","confidence":0.0027204074},{"confidence":0.0026612098,"identifier":"P"},{"identifier":"T","confidence":0.002215881},{"identifier":"V","confidence":0.002010034},{"identifier":"U","confidence":0.0017274991},{"confidence":0.001617176,"identifier":"J"},{"identifier":"H","confidence":0.0015579782},{"identifier":"Z","confidence":0.0013380046},{"confidence":0.0011012134,"identifier":"C"},{"confidence":0.0009834905,"identifier":"K"},{"identifier":"Q","confidence":0.00095725514},{"identifier":"Blank","confidence":0.00073391804},{"identifier":"X","confidence":0.0005842418},{"confidence":0.00030355685,"identifier":"Y"},{"confidence":0.00027530335,"identifier":"L"},{"identifier":"S","confidence":0.00018936566},{"identifier":"Board","confidence":4.2716587e-05}],"coordinates":{"x":0.6171875,"height":0.04974365234375,"y":0.478759765625,"width":0.022491455078125}},{"classifications":[{"identifier":"V","confidence":0.7249499},{"confidence":0.15198328,"identifier":"I"},{"identifier":"Y","confidence":0.084257245},{"confidence":0.024039498,"identifier":"H"},{"confidence":0.0037649616,"identifier":"Z"},{"confidence":0.001511935,"identifier":"N"},{"identifier":"W","confidence":0.0012779773},{"identifier":"B","confidence":0.0012434922},{"confidence":0.0011650556,"identifier":"F"},{"identifier":"T","confidence":0.0009953347},{"identifier":"X","confidence":0.00092839304},{"confidence":0.00085604197,"identifier":"G"},{"confidence":0.0005520997,"identifier":"R"},{"identifier":"J","confidence":0.00043004952},{"identifier":"A","confidence":0.00039657866},{"identifier":"M","confidence":0.0003482319},{"confidence":0.0002819664,"identifier":"Q"},{"identifier":"S","confidence":0.00021046055},{"confidence":0.00019626081,"identifier":"P"},{"confidence":0.00019000615,"identifier":"C"},{"confidence":0.0001837515,"identifier":"O"},{"identifier":"U","confidence":8.469135e-05},{"identifier":"K","confidence":4.9530074e-05},{"confidence":4.496587e-05,"identifier":"D"},{"confidence":2.5018604e-05,"identifier":"E"},{"confidence":1.5721149e-05,"identifier":"Blank"},{"confidence":1.0311722e-05,"identifier":"L"},{"identifier":"Board","confidence":7.2689186e-06}],"coordinates":{"height":0.0472412109375,"y":0.7802734375,"x":0.33984375,"width":0.022979736328125}}],"imagePath":"\/Users\/teerthrajparmar\/development\/BoardSolverData\/finalRotatedImages\/test\/rotated_IMG_7837_jpg.rf.48ddfb5b62aa003475db55a20b64f9d5.jpg"},{"annotations":[{"label":"Board","coordinates":{"width":0.8203125,"x":0.575,"y":0.671875,"height":0.4843750000000001}},{"label":"E","coordinates":{"width":0.05234375,"y":0.88828125,"height":0.03515625,"x":0.946875}},{"label":"J","coordinates":{"height":0.03515625,"y":0.8546875,"x":0.8921875,"width":0.0515625}},{"coordinates":{"width":0.04765625,"y":0.85703125,"height":0.03125,"x":0.84296875},"label":"C"},{"label":"I","coordinates":{"height":0.03359375,"x":0.8828125,"y":0.7828125,"width":0.05234375}},{"label":"H","coordinates":{"height":0.03359375,"x":0.834375,"width":0.05,"y":0.78359375}},{"coordinates":{"y":0.75078125,"height":0.03046875,"width":0.0515625,"x":0.88125},"label":"A"},{"label":"O","coordinates":{"width":0.05,"x":0.83203125,"y":0.7515625,"height":0.0328125}},{"coordinates":{"x":0.78359375,"y":0.7515625,"width":0.05,"height":0.03359375},"label":"R"},{"label":"N","coordinates":{"x":0.83046875,"height":0.03125,"width":0.05,"y":0.7203125}},{"label":"S","coordinates":{"height":0.03125,"width":0.04765625,"y":0.81875,"x":0.6265625}},{"label":"G","coordinates":{"y":0.815625,"height":0.0328125,"width":0.0484375,"x":0.575}},{"label":"I","coordinates":{"x":0.52734375,"y":0.8171875,"width":0.0484375,"height":0.03046875}},{"label":"W","coordinates":{"height":0.03515625,"x":0.4703125,"y":0.85078125,"width":0.05}},{"coordinates":{"height":0.034375,"width":0.0484375,"y":0.81875,"x":0.475},"label":"X"},{"label":"A","coordinates":{"height":0.03125,"width":0.05,"y":0.78359375,"x":0.57578125}},{"coordinates":{"x":0.57109375,"width":0.05,"y":0.74921875,"height":0.03359375},"label":"A"},{"label":"A","coordinates":{"width":0.04765625,"height":0.0328125,"x":0.52734375,"y":0.78359375}},{"label":"V","coordinates":{"y":0.81796875,"x":0.3140625,"width":0.04765625,"height":0.0328125}},{"coordinates":{"height":0.03359375,"y":0.81875,"x":0.26484375,"width":0.04609375},"label":"H"},{"coordinates":{"height":0.034375,"width":0.04921875,"y":0.85078125,"x":0.25859375},"label":"Y"},{"label":"I","coordinates":{"x":0.25703125,"height":0.0328125,"width":0.0484375,"y":0.88359375}},{"coordinates":{"width":0.04609375,"x":0.2078125,"height":0.03203125,"y":0.8828125},"label":"Y"},{"label":"Z","coordinates":{"height":0.03359375,"width":0.04609375,"x":0.21015625,"y":0.85}},{"label":"R","coordinates":{"height":0.02890625,"y":0.6859374999999999,"x":0.32578125,"width":0.046875}},{"coordinates":{"height":0.0296875,"x":0.27734375,"width":0.04765625,"y":0.684375},"label":"O"},{"coordinates":{"y":0.6851562499999999,"x":0.22578125,"height":0.03125,"width":0.04765625},"label":"Q"},{"label":"T","coordinates":{"y":0.6554687499999999,"width":0.04453125,"height":0.02890625,"x":0.32578125}},{"label":"T","coordinates":{"height":0.02890625,"y":0.6539062499999999,"width":0.0453125,"x":0.27734375}},{"coordinates":{"x":0.77109375,"y":0.6546875,"width":0.05,"height":0.03046875},"label":"O"},{"label":"F","coordinates":{"x":0.7234375,"height":0.028125,"width":0.04921875,"y":0.6546875}},{"coordinates":{"x":0.6765625,"y":0.6546875,"height":0.028125,"width":0.04921875},"label":"N"},{"label":"D","coordinates":{"y":0.625,"x":0.7203125,"width":0.04921875,"height":0.03046875}},{"coordinates":{"width":0.05078125,"x":0.6734375,"y":0.62578125,"height":0.02890625},"label":"G"},{"coordinates":{"height":0.02890625,"width":0.05,"x":0.71171875,"y":0.5953125},"label":"O"},{"label":"M","coordinates":{"x":0.47421875,"y":0.65390625,"width":0.046875,"height":0.03046875000000009}},{"label":"R","coordinates":{"height":0.03046875,"y":0.62421875,"width":0.04843750000000009,"x":0.5203125}},{"coordinates":{"height":0.028906250000000088,"x":0.47265625,"y":0.625,"width":0.04843750000000009},"label":"E"},{"label":"A","coordinates":{"height":0.028906250000000088,"y":0.5953125,"x":0.5195312500000001,"width":0.046875}},{"label":"L","coordinates":{"x":0.4718750000000001,"y":0.5953125,"height":0.028906250000000088,"width":0.04453125}},{"label":"I","coordinates":{"x":0.4710937500000001,"height":0.02734375,"y":0.5656249999999999,"width":0.04609375}},{"coordinates":{"x":0.4257812500000001,"y":0.5640624999999999,"height":0.028125,"width":0.0453125},"label":"N"},{"label":"K","coordinates":{"y":0.50859375,"width":0.0484375,"x":0.90703125,"height":0.0296875}},{"label":"P","coordinates":{"width":0.0484375,"x":0.9015625,"height":0.0296875,"y":0.48046875}},{"label":"V","coordinates":{"y":0.4515625,"x":0.9046875,"height":0.02734375,"width":0.04609375}},{"coordinates":{"y":0.4515625,"width":0.04765625,"x":0.85703125,"height":0.0265625},"label":"A"},{"coordinates":{"height":0.02890625,"width":0.046875,"y":0.5359375,"x":0.7625},"label":"U"},{"coordinates":{"width":0.0453125,"y":0.50859375,"x":0.7609375,"height":0.028125},"label":"U"},{"coordinates":{"y":0.48125,"x":0.7578125,"height":0.02734375,"width":0.04765625},"label":"R"},{"label":"L","coordinates":{"x":0.75390625,"width":0.046093750000000086,"height":0.028125,"y":0.45390625}},{"label":"I","coordinates":{"x":0.7125,"y":0.48125,"width":0.04765625,"height":0.028125}},{"coordinates":{"x":0.709375,"y":0.4546875,"width":0.04765625000000009,"height":0.02890625},"label":"E"},{"coordinates":{"width":0.04843749999999991,"y":0.565625,"x":0.61953125,"height":0.028125000000000087},"label":"E"},{"coordinates":{"width":0.04687499999999991,"x":0.6171875,"height":0.028125000000000087,"y":0.5375},"label":"O"},{"label":"D","coordinates":{"x":0.56953125,"height":0.028125,"y":0.5374999999999999,"width":0.04609375}},{"coordinates":{"y":0.509375,"width":0.04609374999999991,"height":0.02656250000000009,"x":0.615625},"label":"E"},{"coordinates":{"height":0.02578125,"x":0.5710937500000001,"width":0.04453125,"y":0.5109374999999999},"label":"M"},{"coordinates":{"height":0.02890625,"x":0.5265625,"width":0.0421875,"y":0.5101562499999999},"label":"L"},{"coordinates":{"x":0.33125000000000016,"width":0.0453125,"height":0.02890625,"y":0.5374999999999999},"label":"U"},{"label":"I","coordinates":{"y":0.50859375,"height":0.02578125,"x":0.3320312500000001,"width":0.046875}},{"label":"B","coordinates":{"x":0.28750000000000014,"y":0.5093749999999999,"width":0.04375,"height":0.0265625}},{"label":"N","coordinates":{"height":0.02734375,"y":0.5093749999999999,"width":0.0453125,"x":0.24218750000000008}},{"label":"S","coordinates":{"y":0.4828124999999999,"width":0.0453125,"height":0.02578125,"x":0.3320312500000001}},{"label":"P","coordinates":{"height":0.02890625,"x":0.28671875000000013,"y":0.4804687499999999,"width":0.04375}},{"coordinates":{"height":0.0265625,"x":0.2414062500000001,"y":0.4812499999999999,"width":0.04453125},"label":"R"}],"imagePath":"\/Users\/teerthrajparmar\/development\/BoardSolverData\/finalRotatedImages\/test\/rotated_IMG_7838_jpg.rf.51871dbdf1f029087c6b59f034a9653c.jpg","inferences":[{"classifications":[{"confidence":0.67126524,"identifier":"A"},{"confidence":0.17752863,"identifier":"C"},{"identifier":"J","confidence":0.045536496},{"confidence":0.036839183,"identifier":"G"},{"confidence":0.015673073,"identifier":"S"},{"identifier":"N","confidence":0.012608116},{"identifier":"F","confidence":0.0078365365},{"confidence":0.0070503945,"identifier":"W"},{"identifier":"Q","confidence":0.0061199614},{"identifier":"O","confidence":0.004955676},{"confidence":0.0024828136,"identifier":"X"},{"identifier":"T","confidence":0.0021929862},{"confidence":0.0015921851,"identifier":"K"},{"confidence":0.0014926735,"identifier":"Y"},{"identifier":"I","confidence":0.0012762359},{"confidence":0.0012022242,"identifier":"V"},{"identifier":"H","confidence":0.001121371},{"identifier":"R","confidence":0.00094287214},{"identifier":"D","confidence":0.0009024455},{"identifier":"L","confidence":0.0004027109},{"confidence":0.00039804628,"identifier":"U"},{"confidence":0.0003243455,"identifier":"P"},{"confidence":9.702378e-05,"identifier":"E"},{"identifier":"Z","confidence":7.6810495e-05},{"identifier":"B","confidence":3.482905e-05},{"confidence":1.9902314e-05,"identifier":"Blank"},{"confidence":1.6948065e-05,"identifier":"M"},{"identifier":"Board","confidence":1.0262131e-05}],"coordinates":{"x":0.560546875,"y":0.7734375,"height":0.032989501953125,"width":0.04931640625}}]}]}},"createdDate":"2024-11-01T20:41:25Z","id":"f7a35de1-b25e-484a-831b-ea18f19156b2"}],"trainingEvaluationEntity":{"analysedDataType":"none","id":"614902f9-3829-4179-a29c-18f0c44f253e","dataResult":{"dataSourceID":"49E1FB54-40D0-4E54-8FF6-4B6AF3BC6C75","itemsCount":48,"dataURL":"file:\/\/\/Users\/teerthrajparmar\/development\/BoardSolverData\/finalRotatedImages\/train\/","dataAnalysis":{"issues":[{"description":"28 classes found, including A, I, E","severity":"debug"},{"severity":"warning","description":"Less than 50 total images found - add more to improve model validation"},{"description":"Smallest class is \"J\" with 36 images","severity":"debug"},{"description":"Largest class is \"A\" with 276 images","severity":"debug"}],"classifierAnalysis":{},"objectDetectorAnalysis":{"labelStats":{"N":144,"R":174,"S":81,"Blank":45,"G":60,"Z":45,"K":42,"Y":42,"J":36,"P":84,"E":264,"L":132,"Q":39,"Board":48,"D":96,"W":75,"X":51,"O":180,"V":75,"C":51,"F":42,"I":270,"M":96,"H":81,"B":57,"A":276,"T":129,"U":144},"details":{}},"summary":{"suggestedMaxIterations":17000,"canUseValidation":1,"sampleCount":48,"classCount":28,"counterExamples":0}},"classesCount":28,"createdDate":"2024-11-01T20:30:48Z"},"dataSourceID":"49E1FB54-40D0-4E54-8FF6-4B6AF3BC6C75","createdDate":"2024-11-01T20:30:48Z"},"modifiedDate":"2024-11-01T20:41:29Z","id":"8f91078b-4371-474b-bbfb-81b7bcd052b9","previewType":"objectDetector","testingEvaluationEntity":{"dataSourceID":"F3942739-C296-4D38-8CE9-EEE291DB399A","analysedDataType":"datasource","createdDate":"2024-11-01T20:30:48Z","id":"8564fb9c-8758-4ec2-8af7-de5d9619cb80","dataResult":{"dataAnalysis":{"issues":[{"description":"27 classes found, including A, I, R","severity":"debug"},{"severity":"warning","description":"Less than 50 total images found - add more to improve model validation"},{"severity":"debug","description":"Smallest class is \"C\" with 1 images"},{"severity":"debug","description":"Largest class is \"A\" with 24 images"}],"classifierAnalysis":{},"summary":{"counterExamples":0,"classCount":27,"canUseValidation":1,"sampleCount":4,"suggestedMaxIterations":5000},"objectDetectorAnalysis":{"labelStats":{"Board":5,"V":4,"D":8,"X":4,"H":8,"L":12,"S":8,"I":24,"O":12,"K":2,"B":3,"Y":4,"N":14,"C":1,"R":19,"Q":4,"U":12,"M":7,"T":8,"J":3,"G":8,"Z":4,"F":4,"W":2,"A":24,"P":6,"E":18},"details":{}}},"createdDate":"2024-11-01T20:30:48Z","itemsCount":4,"dataSourceID":"F3942739-C296-4D38-8CE9-EEE291DB399A","classesCount":27,"dataURL":"file:\/\/\/Users\/teerthrajparmar\/development\/BoardSolverData\/finalRotatedImages\/test\/"}},"validationEvaluationEntity":{"createdDate":"2024-11-01T20:30:48Z","dataResult":{"dataURL":"file:\/\/\/Users\/teerthrajparmar\/development\/BoardSolverData\/finalRotatedImages\/valid\/","dataAnalysis":{"objectDetectorAnalysis":{"details":{},"labelStats":{"P":5,"D":5,"C":2,"O":10,"R":10,"X":4,"E":17,"L":7,"J":2,"Z":2,"U":8,"N":8,"Board":3,"S":3,"W":3,"Q":1,"I":13,"V":5,"Y":2,"B":4,"F":1,"K":2,"Blank":4,"T":8,"A":18,"M":6,"G":6,"H":4}},"issues":[{"description":"28 classes found, including A, E, I","severity":"debug"},{"description":"Less than 50 total images found - add more to improve model validation","severity":"warning"},{"severity":"debug","description":"Smallest class is \"Q\" with 1 images"},{"description":"Largest class is \"A\" with 18 images","severity":"debug"}],"classifierAnalysis":{},"summary":{"classCount":28,"suggestedMaxIterations":4000,"canUseValidation":1,"counterExamples":0,"sampleCount":3}},"dataSourceID":"1518180A-7840-49F1-B4DC-AA181FA96891","createdDate":"2024-11-01T20:30:48Z","itemsCount":3,"classesCount":28},"analysedDataType":"datasource","dataSourceID":"1518180A-7840-49F1-B4DC-AA181FA96891","id":"1eb1518f-7564-4fa5-86f9-bb504b1ac637"}},"version":"1.0","validationEntity":{"dataSourceID":"1518180A-7840-49F1-B4DC-AA181FA96891","dataResult":{"dataAnalysis":{"issues":[{"severity":"debug","description":"28 classes found, including A, E, I"},{"severity":"warning","description":"Less than 50 total images found - add more to improve model validation"},{"severity":"debug","description":"Smallest class is \"Q\" with 1 images"},{"severity":"debug","description":"Largest class is \"A\" with 18 images"}],"summary":{"sampleCount":3,"canUseValidation":1,"suggestedMaxIterations":4000,"counterExamples":0,"classCount":28},"classifierAnalysis":{},"objectDetectorAnalysis":{"labelStats":{"P":5,"X":4,"A":18,"N":8,"Board":3,"H":4,"V":5,"L":7,"R":10,"Blank":4,"Z":2,"M":6,"G":6,"C":2,"B":4,"E":17,"F":1,"D":5,"S":3,"O":10,"W":3,"U":8,"Q":1,"Y":2,"K":2,"J":2,"T":8,"I":13},"details":{}}},"dataSourceID":"1518180A-7840-49F1-B4DC-AA181FA96891","dataURL":"file:\/\/\/Users\/teerthrajparmar\/development\/BoardSolverData\/finalRotatedImages\/valid\/","classesCount":28,"itemsCount":3,"createdDate":"2024-11-01T20:30:48Z"},"analysedDataType":"datasource"},"contentDataResult":{"createdDate":"2024-11-01T20:21:59Z"},"createdDate":"2024-11-01T20:30:48Z","activityEntities":["validationDataAdded",[{"subtitle":"valid","createdDate":"2024-11-01T20:22:13Z","event":"validationDataAdded","title":"Validation Data Added","id":"171B8509-34A3-47B8-968D-3F58EADA357A"}],"trainingStarted",[{"event":"trainingStarted","id":"6E24628C-2B86-46D3-9F59-C4C19241F876","subtitle":"1,200 iterations","title":"Training Started","createdDate":"2024-11-01T20:22:23Z"}],"evaluationFinished",[{"id":"8A2B6492-62AE-4F59-B148-8DBA90020598","event":"evaluationFinished","title":"Testing Completed","subtitle":"Iteration 610","createdDate":"2024-11-01T20:41:29Z"}],"experimentCreated",[{"subtitle":"scrabbleDetectorWithRotation 2","event":"experimentCreated","createdDate":"2024-11-01T20:21:51Z","title":"Model Source Created","id":"BB0C3AE8-9F40-4822-8FBC-B2788F011D32"}],"snapshotCreated",[{"title":"Snapshot Saved","event":"snapshotCreated","id":"FE0A70AC-1722-415F-9299-D1AECA34D088","createdDate":"2024-11-01T20:24:27Z","subtitle":"Snapshot created at iteration 150"},{"id":"2FDCCDE8-5942-40E0-B076-66D5789F4405","subtitle":"Snapshot created at iteration 270","createdDate":"2024-11-01T20:26:11Z","event":"snapshotCreated","title":"Snapshot Saved"}],"trainingDataAdded",[{"createdDate":"2024-11-01T20:22:11Z","subtitle":"train","id":"AA880BB5-9E21-4775-AE90-CF279D98EA6A","event":"trainingDataAdded","title":"Training Data Added"}],"evaluationStarted",[{"createdDate":"2024-11-01T20:41:28Z","id":"CF522950-B07B-495A-8D4F-6693A13D2077","event":"evaluationStarted","title":"Testing Started","subtitle":"Iteration 610"}]],"id":"7FD44851-CE76-4D8F-BC23-DDCD15EED14D","settingEntity":{"featureNames":[],"recommendedIterationCount":17000,"odAlgorithmType":"darknetYolo","harVideoAugmentations":0,"handActionClassifierAugmentations":[],"taskType":"objectDetector","seedType":"default","algorithmType":"maxEnt","odGridWidth":10,"transferLearningEmbeddingType":"dynamic","augmentations":[],"styleTransferAlgorithmType":"image","handPoseClassifierAugmentations":[],"iterationCount":1200,"odGridHeight":10},"snapshotRole":{"snapshotIteration":610,"snapshotParent":"760DAA1F-53F5-4198-B2A9-D6A73D4D10C7"},"state":"trained","evaluationEntity":{"id":"26c51ddd-713f-4242-a6f2-eba2b4a85637","dataResult":{},"analysedDataType":"none"}}